{
  "matchId": 31909672,
  "opponent": "T\u00e4by Bullcats",
  "homeOrAway": "home",
  "location": "Thorildshallen",
  "dateLabel": "Sun 9.Feb 16:15",
  "timeline": [
    {
      "period": 1,
      "clock": "00:00",
      "teamId": null,
      "teamName": "T\u00e4by Bullcats",
      "player": "",
      "playerNumber": "",
      "score": "0-0",
      "rawType": 97,
      "side": null,
      "kind": "period",
      "label": "Start Period 1",
      "emoji": "\u23f1\ufe0f"
    },
    {
      "period": 1,
      "clock": null,
      "teamId": 1260452,
      "teamName": "T\u00e4by Bullcats",
      "player": "Christoffer Lagerstam",
      "playerNumber": "8",
      "score": "0-2",
      "rawType": 104,
      "side": "Opponent",
      "kind": "score",
      "label": "2PT Made",
      "emoji": "\ud83c\udfc0"
    },
    {
      "period": 1,
      "clock": null,
      "teamId": 1260452,
      "teamName": "T\u00e4by Bullcats",
      "player": "Victor Silbersky",
      "playerNumber": "5",
      "score": "0-4",
      "rawType": 104,
      "side": "Opponent",
      "kind": "score",
      "label": "2PT Made",
      "emoji": "\ud83c\udfc0"
    },
    {
      "period": 1,
      "clock": null,
      "teamId": 1264914,
      "teamName": "Kungsholmen OG",
      "player": "Nessim Al Khalili",
      "playerNumber": "1",
      "score": "0-4",
      "rawType": 109,
      "side": "KOG",
      "kind": "foul",
      "label": "Personal Foul",
      "emoji": "\ud83e\udd4a"
    },
    {
      "period": 1,
      "clock": null,
      "teamId": 1260452,
      "teamName": "T\u00e4by Bullcats",
      "player": "Victor Silbersky",
      "playerNumber": "5",
      "score": "0-7",
      "rawType": 103,
      "side": "Opponent",
      "kind": "score",
      "label": "3PT Made",
      "emoji": "\ud83c\udfaf"
    },
    {
      "period": 1,
      "clock": null,
      "teamId": 1260452,
      "teamName": "T\u00e4by Bullcats",
      "player": "Olof Andersson",
      "playerNumber": "6",
      "score": "0-9",
      "rawType": 104,
      "side": "Opponent",
      "kind": "score",
      "label": "2PT Made",
      "emoji": "\ud83c\udfc0"
    },
    {
      "period": 1,
      "clock": null,
      "teamId": 1260452,
      "teamName": "T\u00e4by Bullcats",
      "player": "Olof Andersson",
      "playerNumber": "6",
      "score": "0-9",
      "rawType": 109,
      "side": "Opponent",
      "kind": "foul",
      "label": "Personal Foul",
      "emoji": "\ud83e\udd4a"
    },
    {
      "period": 1,
      "clock": null,
      "teamId": 1264914,
      "teamName": "Kungsholmen OG",
      "player": "Nicholas Frederiksen",
      "playerNumber": "36",
      "score": "2-9",
      "rawType": 104,
      "side": "KOG",
      "kind": "score",
      "label": "2PT Made",
      "emoji": "\ud83c\udfc0"
    },
    {
      "period": 1,
      "clock": null,
      "teamId": 1260452,
      "teamName": "T\u00e4by Bullcats",
      "player": "Christoffer Lagerstam",
      "playerNumber": "8",
      "score": "2-11",
      "rawType": 104,
      "side": "Opponent",
      "kind": "score",
      "label": "2PT Made",
      "emoji": "\ud83c\udfc0"
    },
    {
      "period": 1,
      "clock": null,
      "teamId": 1264914,
      "teamName": "Kungsholmen OG",
      "player": "Nicholas Frederiksen",
      "playerNumber": "36",
      "score": "5-11",
      "rawType": 103,
      "side": "KOG",
      "kind": "score",
      "label": "3PT Made",
      "emoji": "\ud83c\udfaf"
    },
    {
      "period": 1,
      "clock": null,
      "teamId": 1260452,
      "teamName": "T\u00e4by Bullcats",
      "player": "Victor Silbersky",
      "playerNumber": "5",
      "score": "5-14",
      "rawType": 103,
      "side": "Opponent",
      "kind": "score",
      "label": "3PT Made",
      "emoji": "\ud83c\udfaf"
    },
    {
      "period": 1,
      "clock": null,
      "teamId": 1264914,
      "teamName": "Kungsholmen OG",
      "player": "Nessim Al Khalili",
      "playerNumber": "1",
      "score": "7-14",
      "rawType": 104,
      "side": "KOG",
      "kind": "score",
      "label": "2PT Made",
      "emoji": "\ud83c\udfc0"
    },
    {
      "period": 1,
      "clock": null,
      "teamId": 1264914,
      "teamName": "Kungsholmen OG",
      "player": "Lucas Evertsson",
      "playerNumber": "10",
      "score": "10-14",
      "rawType": 103,
      "side": "KOG",
      "kind": "score",
      "label": "3PT Made",
      "emoji": "\ud83c\udfaf"
    },
    {
      "period": 1,
      "clock": null,
      "teamId": 1264914,
      "teamName": "Kungsholmen OG",
      "player": "Kipat Kahumbu",
      "playerNumber": "41",
      "score": "10-14",
      "rawType": 109,
      "side": "KOG",
      "kind": "foul",
      "label": "Personal Foul",
      "emoji": "\ud83e\udd4a"
    },
    {
      "period": 1,
      "clock": null,
      "teamId": 1260452,
      "teamName": "T\u00e4by Bullcats",
      "player": "Emil Svantesson",
      "playerNumber": "10",
      "score": "10-15",
      "rawType": 106,
      "side": "Opponent",
      "kind": "score",
      "label": "FT Made",
      "emoji": "\ud83c\udfab"
    },
    {
      "period": 1,
      "clock": null,
      "teamId": 1260452,
      "teamName": "T\u00e4by Bullcats",
      "player": "Emil Svantesson",
      "playerNumber": "10",
      "score": "10-16",
      "rawType": 106,
      "side": "Opponent",
      "kind": "score",
      "label": "FT Made",
      "emoji": "\ud83c\udfab"
    },
    {
      "period": 1,
      "clock": null,
      "teamId": 1264914,
      "teamName": "Kungsholmen OG",
      "player": "Nessim Al Khalili",
      "playerNumber": "1",
      "score": "12-16",
      "rawType": 104,
      "side": "KOG",
      "kind": "score",
      "label": "2PT Made",
      "emoji": "\ud83c\udfc0"
    },
    {
      "period": 1,
      "clock": null,
      "teamId": 1260452,
      "teamName": "T\u00e4by Bullcats",
      "player": "Martin B\u00f6hlin",
      "playerNumber": "12",
      "score": "12-19",
      "rawType": 103,
      "side": "Opponent",
      "kind": "score",
      "label": "3PT Made",
      "emoji": "\ud83c\udfaf"
    },
    {
      "period": 1,
      "clock": null,
      "teamId": 1260452,
      "teamName": "T\u00e4by Bullcats",
      "player": "Martin B\u00f6hlin",
      "playerNumber": "12",
      "score": "12-21",
      "rawType": 104,
      "side": "Opponent",
      "kind": "score",
      "label": "2PT Made",
      "emoji": "\ud83c\udfc0"
    },
    {
      "period": 1,
      "clock": null,
      "teamId": 1260452,
      "teamName": "T\u00e4by Bullcats",
      "player": "Martin B\u00f6hlin",
      "playerNumber": "12",
      "score": "12-24",
      "rawType": 103,
      "side": "Opponent",
      "kind": "score",
      "label": "3PT Made",
      "emoji": "\ud83c\udfaf"
    },
    {
      "period": 1,
      "clock": null,
      "teamId": 1260452,
      "teamName": "T\u00e4by Bullcats",
      "player": "Joakim Henriksson",
      "playerNumber": "4",
      "score": "12-27",
      "rawType": 103,
      "side": "Opponent",
      "kind": "score",
      "label": "3PT Made",
      "emoji": "\ud83c\udfaf"
    },
    {
      "period": 1,
      "clock": null,
      "teamId": 1264914,
      "teamName": "Kungsholmen OG",
      "player": "Kipat Kahumbu",
      "playerNumber": "41",
      "score": "14-27",
      "rawType": 104,
      "side": "KOG",
      "kind": "score",
      "label": "2PT Made",
      "emoji": "\ud83c\udfc0"
    },
    {
      "period": 1,
      "clock": null,
      "teamId": 1260452,
      "teamName": "T\u00e4by Bullcats",
      "player": "Emil Svantesson",
      "playerNumber": "10",
      "score": "14-29",
      "rawType": 104,
      "side": "Opponent",
      "kind": "score",
      "label": "2PT Made",
      "emoji": "\ud83c\udfc0"
    },
    {
      "period": 1,
      "clock": null,
      "teamId": 1264914,
      "teamName": "Kungsholmen OG",
      "player": "Nicholas Frederiksen",
      "playerNumber": "36",
      "score": "14-29",
      "rawType": 109,
      "side": "KOG",
      "kind": "foul",
      "label": "Personal Foul",
      "emoji": "\ud83e\udd4a"
    },
    {
      "period": 1,
      "clock": null,
      "teamId": 1260452,
      "teamName": "T\u00e4by Bullcats",
      "player": "Martin B\u00f6hlin",
      "playerNumber": "12",
      "score": "14-30",
      "rawType": 106,
      "side": "Opponent",
      "kind": "score",
      "label": "FT Made",
      "emoji": "\ud83c\udfab"
    },
    {
      "period": 1,
      "clock": null,
      "teamId": 1260452,
      "teamName": "T\u00e4by Bullcats",
      "player": "Martin B\u00f6hlin",
      "playerNumber": "12",
      "score": "14-31",
      "rawType": 106,
      "side": "Opponent",
      "kind": "score",
      "label": "FT Made",
      "emoji": "\ud83c\udfab"
    },
    {
      "period": 1,
      "clock": null,
      "teamId": 1264914,
      "teamName": "Kungsholmen OG",
      "player": "Nicholas Frederiksen",
      "playerNumber": "36",
      "score": "14-31",
      "rawType": 109,
      "side": "KOG",
      "kind": "foul",
      "label": "Personal Foul",
      "emoji": "\ud83e\udd4a"
    },
    {
      "period": 1,
      "clock": null,
      "teamId": 1260452,
      "teamName": "T\u00e4by Bullcats",
      "player": "Christoffer Lagerstam",
      "playerNumber": "8",
      "score": "14-32",
      "rawType": 106,
      "side": "Opponent",
      "kind": "score",
      "label": "FT Made",
      "emoji": "\ud83c\udfab"
    },
    {
      "period": 1,
      "clock": null,
      "teamId": 1264914,
      "teamName": "Kungsholmen OG",
      "player": "Luka Rosko",
      "playerNumber": "11",
      "score": "14-32",
      "rawType": 109,
      "side": "KOG",
      "kind": "foul",
      "label": "Personal Foul",
      "emoji": "\ud83e\udd4a"
    },
    {
      "period": 1,
      "clock": null,
      "teamId": 1260452,
      "teamName": "T\u00e4by Bullcats",
      "player": "Fredrik Benckert",
      "playerNumber": "7",
      "score": "14-33",
      "rawType": 106,
      "side": "Opponent",
      "kind": "score",
      "label": "FT Made",
      "emoji": "\ud83c\udfab"
    },
    {
      "period": 1,
      "clock": null,
      "teamId": 1260452,
      "teamName": "T\u00e4by Bullcats",
      "player": "Fredrik Benckert",
      "playerNumber": "7",
      "score": "14-34",
      "rawType": 106,
      "side": "Opponent",
      "kind": "score",
      "label": "FT Made",
      "emoji": "\ud83c\udfab"
    },
    {
      "period": 1,
      "clock": null,
      "teamId": 1264914,
      "teamName": "Kungsholmen OG",
      "player": "Lucas Evertsson",
      "playerNumber": "10",
      "score": "16-34",
      "rawType": 104,
      "side": "KOG",
      "kind": "score",
      "label": "2PT Made",
      "emoji": "\ud83c\udfc0"
    },
    {
      "period": 1,
      "clock": null,
      "teamId": 1260452,
      "teamName": "T\u00e4by Bullcats",
      "player": "Olof Andersson",
      "playerNumber": "6",
      "score": "16-36",
      "rawType": 104,
      "side": "Opponent",
      "kind": "score",
      "label": "2PT Made",
      "emoji": "\ud83c\udfc0"
    },
    {
      "period": 1,
      "clock": null,
      "teamId": 1260452,
      "teamName": "T\u00e4by Bullcats",
      "player": "Fredrik Benckert",
      "playerNumber": "7",
      "score": "16-38",
      "rawType": 104,
      "side": "Opponent",
      "kind": "score",
      "label": "2PT Made",
      "emoji": "\ud83c\udfc0"
    },
    {
      "period": 1,
      "clock": null,
      "teamId": 1260452,
      "teamName": "T\u00e4by Bullcats",
      "player": "Victor By",
      "playerNumber": "13",
      "score": "16-38",
      "rawType": 109,
      "side": "Opponent",
      "kind": "foul",
      "label": "Personal Foul",
      "emoji": "\ud83e\udd4a"
    },
    {
      "period": 1,
      "clock": null,
      "teamId": 1260452,
      "teamName": "T\u00e4by Bullcats",
      "player": "Emil Svantesson",
      "playerNumber": "10",
      "score": "16-40",
      "rawType": 104,
      "side": "Opponent",
      "kind": "score",
      "label": "2PT Made",
      "emoji": "\ud83c\udfc0"
    },
    {
      "period": 1,
      "clock": null,
      "teamId": 1264914,
      "teamName": "Kungsholmen OG",
      "player": "Luka Rosko",
      "playerNumber": "11",
      "score": "16-40",
      "rawType": 109,
      "side": "KOG",
      "kind": "foul",
      "label": "Personal Foul",
      "emoji": "\ud83e\udd4a"
    },
    {
      "period": 1,
      "clock": null,
      "teamId": 1260452,
      "teamName": "T\u00e4by Bullcats",
      "player": "Victor By",
      "playerNumber": "13",
      "score": "16-41",
      "rawType": 106,
      "side": "Opponent",
      "kind": "score",
      "label": "FT Made",
      "emoji": "\ud83c\udfab"
    },
    {
      "period": 1,
      "clock": null,
      "teamId": 1264914,
      "teamName": "Kungsholmen OG",
      "player": "Luka Rosko",
      "playerNumber": "11",
      "score": "16-41",
      "rawType": 109,
      "side": "KOG",
      "kind": "foul",
      "label": "Personal Foul",
      "emoji": "\ud83e\udd4a"
    },
    {
      "period": 1,
      "clock": null,
      "teamId": 1260452,
      "teamName": "T\u00e4by Bullcats",
      "player": "Victor By",
      "playerNumber": "13",
      "score": "16-42",
      "rawType": 106,
      "side": "Opponent",
      "kind": "score",
      "label": "FT Made",
      "emoji": "\ud83c\udfab"
    },
    {
      "period": 1,
      "clock": "10:00",
      "teamId": null,
      "teamName": "T\u00e4by Bullcats",
      "player": "",
      "playerNumber": "",
      "score": "16-42",
      "rawType": 98,
      "side": null,
      "kind": "period",
      "label": "End Period 1",
      "emoji": "\ud83d\udd14",
      "detail": "T\u00e4by Bullcats wins QTR 42-16, lead -26"
    },
    {
      "period": 2,
      "clock": "00:00",
      "teamId": null,
      "teamName": "T\u00e4by Bullcats",
      "player": "",
      "playerNumber": "",
      "score": "16-42",
      "rawType": 99,
      "side": null,
      "kind": "period",
      "label": "Start Period 2",
      "emoji": "\u23f1\ufe0f"
    },
    {
      "period": 2,
      "clock": null,
      "teamId": 1260452,
      "teamName": "T\u00e4by Bullcats",
      "player": "Martin B\u00f6hlin",
      "playerNumber": "12",
      "score": "16-44",
      "rawType": 104,
      "side": "Opponent",
      "kind": "score",
      "label": "2PT Made",
      "emoji": "\ud83c\udfc0"
    },
    {
      "period": 2,
      "clock": null,
      "teamId": 1264914,
      "teamName": "Kungsholmen OG",
      "player": "Nessim Al Khalili",
      "playerNumber": "1",
      "score": "16-44",
      "rawType": 109,
      "side": "KOG",
      "kind": "foul",
      "label": "Personal Foul",
      "emoji": "\ud83e\udd4a"
    },
    {
      "period": 2,
      "clock": null,
      "teamId": 1260452,
      "teamName": "T\u00e4by Bullcats",
      "player": "Christoffer Lagerstam",
      "playerNumber": "8",
      "score": "16-45",
      "rawType": 106,
      "side": "Opponent",
      "kind": "score",
      "label": "FT Made",
      "emoji": "\ud83c\udfab"
    },
    {
      "period": 2,
      "clock": null,
      "teamId": 1260452,
      "teamName": "T\u00e4by Bullcats",
      "player": "Joakim Henriksson",
      "playerNumber": "4",
      "score": "16-48",
      "rawType": 103,
      "side": "Opponent",
      "kind": "score",
      "label": "3PT Made",
      "emoji": "\ud83c\udfaf"
    },
    {
      "period": 2,
      "clock": null,
      "teamId": 1264914,
      "teamName": "Kungsholmen OG",
      "player": "Lucas Evertsson",
      "playerNumber": "10",
      "score": "18-48",
      "rawType": 104,
      "side": "KOG",
      "kind": "score",
      "label": "2PT Made",
      "emoji": "\ud83c\udfc0"
    },
    {
      "period": 2,
      "clock": null,
      "teamId": 1260452,
      "teamName": "T\u00e4by Bullcats",
      "player": "Joakim Henriksson",
      "playerNumber": "4",
      "score": "18-50",
      "rawType": 104,
      "side": "Opponent",
      "kind": "score",
      "label": "2PT Made",
      "emoji": "\ud83c\udfc0"
    },
    {
      "period": 2,
      "clock": null,
      "teamId": 1264914,
      "teamName": "Kungsholmen OG",
      "player": "Kipat Kahumbu",
      "playerNumber": "41",
      "score": "18-50",
      "rawType": 109,
      "side": "KOG",
      "kind": "foul",
      "label": "Personal Foul",
      "emoji": "\ud83e\udd4a"
    },
    {
      "period": 2,
      "clock": null,
      "teamId": 1260452,
      "teamName": "T\u00e4by Bullcats",
      "player": "Joakim Henriksson",
      "playerNumber": "4",
      "score": "18-50",
      "rawType": 109,
      "side": "Opponent",
      "kind": "foul",
      "label": "Personal Foul",
      "emoji": "\ud83e\udd4a"
    },
    {
      "period": 2,
      "clock": null,
      "teamId": 1260452,
      "teamName": "T\u00e4by Bullcats",
      "player": "Victor By",
      "playerNumber": "13",
      "score": "18-52",
      "rawType": 104,
      "side": "Opponent",
      "kind": "score",
      "label": "2PT Made",
      "emoji": "\ud83c\udfc0"
    },
    {
      "period": 2,
      "clock": null,
      "teamId": 1260452,
      "teamName": "T\u00e4by Bullcats",
      "player": "Victor Silbersky",
      "playerNumber": "5",
      "score": "18-54",
      "rawType": 104,
      "side": "Opponent",
      "kind": "score",
      "label": "2PT Made",
      "emoji": "\ud83c\udfc0"
    },
    {
      "period": 2,
      "clock": null,
      "teamId": 1260452,
      "teamName": "T\u00e4by Bullcats",
      "player": "Emil Svantesson",
      "playerNumber": "10",
      "score": "18-54",
      "rawType": 109,
      "side": "Opponent",
      "kind": "foul",
      "label": "Personal Foul",
      "emoji": "\ud83e\udd4a"
    },
    {
      "period": 2,
      "clock": null,
      "teamId": 1264914,
      "teamName": "Kungsholmen OG",
      "player": "Anton Jensen Wennberg",
      "playerNumber": "27",
      "score": "19-54",
      "rawType": 106,
      "side": "KOG",
      "kind": "score",
      "label": "FT Made",
      "emoji": "\ud83c\udfab"
    },
    {
      "period": 2,
      "clock": null,
      "teamId": 1264914,
      "teamName": "Kungsholmen OG",
      "player": "Anton Jensen Wennberg",
      "playerNumber": "27",
      "score": "20-54",
      "rawType": 106,
      "side": "KOG",
      "kind": "score",
      "label": "FT Made",
      "emoji": "\ud83c\udfab"
    },
    {
      "period": 2,
      "clock": null,
      "teamId": 1260452,
      "teamName": "T\u00e4by Bullcats",
      "player": "Emil Svantesson",
      "playerNumber": "10",
      "score": "20-57",
      "rawType": 103,
      "side": "Opponent",
      "kind": "score",
      "label": "3PT Made",
      "emoji": "\ud83c\udfaf"
    },
    {
      "period": 2,
      "clock": null,
      "teamId": 1264914,
      "teamName": "Kungsholmen OG",
      "player": "Mikael Ceder Brolin",
      "playerNumber": "8",
      "score": "20-57",
      "rawType": 109,
      "side": "KOG",
      "kind": "foul",
      "label": "Personal Foul",
      "emoji": "\ud83e\udd4a"
    },
    {
      "period": 2,
      "clock": null,
      "teamId": 1260452,
      "teamName": "T\u00e4by Bullcats",
      "player": "Fredrik Benckert",
      "playerNumber": "7",
      "score": "20-58",
      "rawType": 106,
      "side": "Opponent",
      "kind": "score",
      "label": "FT Made",
      "emoji": "\ud83c\udfab"
    },
    {
      "period": 2,
      "clock": null,
      "teamId": 1260452,
      "teamName": "T\u00e4by Bullcats",
      "player": "Fredrik Benckert",
      "playerNumber": "7",
      "score": "20-59",
      "rawType": 106,
      "side": "Opponent",
      "kind": "score",
      "label": "FT Made",
      "emoji": "\ud83c\udfab"
    },
    {
      "period": 2,
      "clock": null,
      "teamId": 1264914,
      "teamName": "Kungsholmen OG",
      "player": "Kipat Kahumbu",
      "playerNumber": "41",
      "score": "22-59",
      "rawType": 104,
      "side": "KOG",
      "kind": "score",
      "label": "2PT Made",
      "emoji": "\ud83c\udfc0"
    },
    {
      "period": 2,
      "clock": null,
      "teamId": 1260452,
      "teamName": "T\u00e4by Bullcats",
      "player": "Christoffer Lagerstam",
      "playerNumber": "8",
      "score": "22-60",
      "rawType": 106,
      "side": "Opponent",
      "kind": "score",
      "label": "FT Made",
      "emoji": "\ud83c\udfab"
    },
    {
      "period": 2,
      "clock": null,
      "teamId": 1264914,
      "teamName": "Kungsholmen OG",
      "player": "Nicholas Frederiksen",
      "playerNumber": "36",
      "score": "24-60",
      "rawType": 104,
      "side": "KOG",
      "kind": "score",
      "label": "2PT Made",
      "emoji": "\ud83c\udfc0"
    },
    {
      "period": 2,
      "clock": null,
      "teamId": 1260452,
      "teamName": "T\u00e4by Bullcats",
      "player": "Fredrik Benckert",
      "playerNumber": "7",
      "score": "24-62",
      "rawType": 104,
      "side": "Opponent",
      "kind": "score",
      "label": "2PT Made",
      "emoji": "\ud83c\udfc0"
    },
    {
      "period": 2,
      "clock": null,
      "teamId": 1264914,
      "teamName": "Kungsholmen OG",
      "player": "Nessim Al Khalili",
      "playerNumber": "1",
      "score": "26-62",
      "rawType": 104,
      "side": "KOG",
      "kind": "score",
      "label": "2PT Made",
      "emoji": "\ud83c\udfc0"
    },
    {
      "period": 2,
      "clock": null,
      "teamId": 1260452,
      "teamName": "T\u00e4by Bullcats",
      "player": "Martin B\u00f6hlin",
      "playerNumber": "12",
      "score": "26-64",
      "rawType": 104,
      "side": "Opponent",
      "kind": "score",
      "label": "2PT Made",
      "emoji": "\ud83c\udfc0"
    },
    {
      "period": 2,
      "clock": null,
      "teamId": 1264914,
      "teamName": "Kungsholmen OG",
      "player": "Kipat Kahumbu",
      "playerNumber": "41",
      "score": "28-64",
      "rawType": 104,
      "side": "KOG",
      "kind": "score",
      "label": "2PT Made",
      "emoji": "\ud83c\udfc0"
    },
    {
      "period": 2,
      "clock": null,
      "teamId": 1260452,
      "teamName": "T\u00e4by Bullcats",
      "player": "Martin B\u00f6hlin",
      "playerNumber": "12",
      "score": "28-67",
      "rawType": 103,
      "side": "Opponent",
      "kind": "score",
      "label": "3PT Made",
      "emoji": "\ud83c\udfaf"
    },
    {
      "period": 2,
      "clock": null,
      "teamId": 1264914,
      "teamName": "Kungsholmen OG",
      "player": "Luka Rosko",
      "playerNumber": "11",
      "score": "30-67",
      "rawType": 104,
      "side": "KOG",
      "kind": "score",
      "label": "2PT Made",
      "emoji": "\ud83c\udfc0"
    },
    {
      "period": 2,
      "clock": null,
      "teamId": 1264914,
      "teamName": "Kungsholmen OG",
      "player": "Kipat Kahumbu",
      "playerNumber": "41",
      "score": "32-67",
      "rawType": 104,
      "side": "KOG",
      "kind": "score",
      "label": "2PT Made",
      "emoji": "\ud83c\udfc0"
    },
    {
      "period": 2,
      "clock": null,
      "teamId": 1264914,
      "teamName": "Kungsholmen OG",
      "player": "Anton Jensen Wennberg",
      "playerNumber": "27",
      "score": "32-67",
      "rawType": 109,
      "side": "KOG",
      "kind": "foul",
      "label": "Personal Foul",
      "emoji": "\ud83e\udd4a"
    },
    {
      "period": 2,
      "clock": null,
      "teamId": 1264914,
      "teamName": "Kungsholmen OG",
      "player": "Kipat Kahumbu",
      "playerNumber": "41",
      "score": "34-67",
      "rawType": 104,
      "side": "KOG",
      "kind": "score",
      "label": "2PT Made",
      "emoji": "\ud83c\udfc0"
    },
    {
      "period": 2,
      "clock": null,
      "teamId": 1260452,
      "teamName": "T\u00e4by Bullcats",
      "player": "Joakim Henriksson",
      "playerNumber": "4",
      "score": "34-69",
      "rawType": 104,
      "side": "Opponent",
      "kind": "score",
      "label": "2PT Made",
      "emoji": "\ud83c\udfc0"
    },
    {
      "period": 2,
      "clock": null,
      "teamId": 1260452,
      "teamName": "T\u00e4by Bullcats",
      "player": "Christoffer Lagerstam",
      "playerNumber": "8",
      "score": "34-70",
      "rawType": 106,
      "side": "Opponent",
      "kind": "score",
      "label": "FT Made",
      "emoji": "\ud83c\udfab"
    },
    {
      "period": 2,
      "clock": null,
      "teamId": 1264914,
      "teamName": "Kungsholmen OG",
      "player": "Kipat Kahumbu",
      "playerNumber": "41",
      "score": "36-70",
      "rawType": 104,
      "side": "KOG",
      "kind": "score",
      "label": "2PT Made",
      "emoji": "\ud83c\udfc0"
    },
    {
      "period": 2,
      "clock": null,
      "teamId": 1260452,
      "teamName": "T\u00e4by Bullcats",
      "player": "Joakim Henriksson",
      "playerNumber": "4",
      "score": "36-72",
      "rawType": 104,
      "side": "Opponent",
      "kind": "score",
      "label": "2PT Made",
      "emoji": "\ud83c\udfc0"
    },
    {
      "period": 2,
      "clock": null,
      "teamId": 1264914,
      "teamName": "Kungsholmen OG",
      "player": "Nicholas Frederiksen",
      "playerNumber": "36",
      "score": "38-72",
      "rawType": 104,
      "side": "KOG",
      "kind": "score",
      "label": "2PT Made",
      "emoji": "\ud83c\udfc0"
    },
    {
      "period": 2,
      "clock": null,
      "teamId": 1260452,
      "teamName": "T\u00e4by Bullcats",
      "player": "Christoffer Lagerstam",
      "playerNumber": "8",
      "score": "38-74",
      "rawType": 104,
      "side": "Opponent",
      "kind": "score",
      "label": "2PT Made",
      "emoji": "\ud83c\udfc0"
    },
    {
      "period": 2,
      "clock": null,
      "teamId": 1264914,
      "teamName": "Kungsholmen OG",
      "player": "Luka Rosko",
      "playerNumber": "11",
      "score": "41-74",
      "rawType": 103,
      "side": "KOG",
      "kind": "score",
      "label": "3PT Made",
      "emoji": "\ud83c\udfaf"
    },
    {
      "period": 2,
      "clock": null,
      "teamId": 1260452,
      "teamName": "T\u00e4by Bullcats",
      "player": "Christoffer Lagerstam",
      "playerNumber": "8",
      "score": "41-76",
      "rawType": 104,
      "side": "Opponent",
      "kind": "score",
      "label": "2PT Made",
      "emoji": "\ud83c\udfc0"
    },
    {
      "period": 2,
      "clock": null,
      "teamId": 1260452,
      "teamName": "T\u00e4by Bullcats",
      "player": "Joakim Henriksson",
      "playerNumber": "4",
      "score": "41-76",
      "rawType": 109,
      "side": "Opponent",
      "kind": "foul",
      "label": "Personal Foul",
      "emoji": "\ud83e\udd4a"
    },
    {
      "period": 2,
      "clock": null,
      "teamId": 1264914,
      "teamName": "Kungsholmen OG",
      "player": "Anton Jensen Wennberg",
      "playerNumber": "27",
      "score": "42-76",
      "rawType": 106,
      "side": "KOG",
      "kind": "score",
      "label": "FT Made",
      "emoji": "\ud83c\udfab"
    },
    {
      "period": 2,
      "clock": null,
      "teamId": 1264914,
      "teamName": "Kungsholmen OG",
      "player": "Anton Jensen Wennberg",
      "playerNumber": "27",
      "score": "43-76",
      "rawType": 106,
      "side": "KOG",
      "kind": "score",
      "label": "FT Made",
      "emoji": "\ud83c\udfab"
    },
    {
      "period": 2,
      "clock": null,
      "teamId": 1264914,
      "teamName": "Kungsholmen OG",
      "player": "Nessim Al Khalili",
      "playerNumber": "1",
      "score": "45-76",
      "rawType": 104,
      "side": "KOG",
      "kind": "score",
      "label": "2PT Made",
      "emoji": "\ud83c\udfc0"
    },
    {
      "period": 2,
      "clock": null,
      "teamId": 1260452,
      "teamName": "T\u00e4by Bullcats",
      "player": "Olof Andersson",
      "playerNumber": "6",
      "score": "45-79",
      "rawType": 103,
      "side": "Opponent",
      "kind": "score",
      "label": "3PT Made",
      "emoji": "\ud83c\udfaf"
    },
    {
      "period": 2,
      "clock": null,
      "teamId": 1264914,
      "teamName": "Kungsholmen OG",
      "player": "Nessim Al Khalili",
      "playerNumber": "1",
      "score": "47-79",
      "rawType": 104,
      "side": "KOG",
      "kind": "score",
      "label": "2PT Made",
      "emoji": "\ud83c\udfc0"
    },
    {
      "period": 2,
      "clock": null,
      "teamId": 1260452,
      "teamName": "T\u00e4by Bullcats",
      "player": "Joakim Henriksson",
      "playerNumber": "4",
      "score": "47-82",
      "rawType": 103,
      "side": "Opponent",
      "kind": "score",
      "label": "3PT Made",
      "emoji": "\ud83c\udfaf"
    },
    {
      "period": 2,
      "clock": null,
      "teamId": 1264914,
      "teamName": "Kungsholmen OG",
      "player": "Kipat Kahumbu",
      "playerNumber": "41",
      "score": "49-82",
      "rawType": 104,
      "side": "KOG",
      "kind": "score",
      "label": "2PT Made",
      "emoji": "\ud83c\udfc0"
    },
    {
      "period": 2,
      "clock": "10:00",
      "teamId": null,
      "teamName": "T\u00e4by Bullcats",
      "player": "",
      "playerNumber": "",
      "score": "49-82",
      "rawType": 98,
      "side": null,
      "kind": "period",
      "label": "End Period 2",
      "emoji": "\ud83d\udd14",
      "detail": "T\u00e4by Bullcats wins QTR 40-33, lead -33"
    },
    {
      "period": 3,
      "clock": "00:00",
      "teamId": null,
      "teamName": "T\u00e4by Bullcats",
      "player": "",
      "playerNumber": "",
      "score": "49-82",
      "rawType": 99,
      "side": null,
      "kind": "period",
      "label": "Start Period 3",
      "emoji": "\u23f1\ufe0f"
    },
    {
      "period": 3,
      "clock": "10:00",
      "teamId": null,
      "teamName": "T\u00e4by Bullcats",
      "player": "",
      "playerNumber": "",
      "score": "49-82",
      "rawType": 98,
      "side": null,
      "kind": "period",
      "label": "End Period 3",
      "emoji": "\ud83d\udd14",
      "detail": "QTR tied 0-0, lead -33"
    },
    {
      "period": 4,
      "clock": "00:00",
      "teamId": null,
      "teamName": "T\u00e4by Bullcats",
      "player": "",
      "playerNumber": "",
      "score": "49-82",
      "rawType": 99,
      "side": null,
      "kind": "period",
      "label": "Start Period 4",
      "emoji": "\u23f1\ufe0f"
    },
    {
      "period": 4,
      "clock": "10:00",
      "teamId": null,
      "teamName": "T\u00e4by Bullcats",
      "player": "",
      "playerNumber": "",
      "score": "49-82",
      "rawType": 100,
      "side": null,
      "kind": "period",
      "label": "End Period 4",
      "emoji": "\ud83d\udd14",
      "detail": "QTR tied 0-0, lead -33"
    },
    {
      "period": 4,
      "clock": "10:00",
      "teamId": null,
      "teamName": "T\u00e4by Bullcats",
      "player": "",
      "playerNumber": "",
      "score": "49-82",
      "rawType": 100,
      "side": "Opponent",
      "kind": "period",
      "label": "Final Buzzer \u2014 T\u00e4by Bullcats",
      "emoji": "\ud83c\udfc1"
    }
  ]
}