{
  "matchId": 31909587,
  "opponent": "T\u00e4by Bullcats",
  "homeOrAway": "away",
  "location": "By\u00e4ngshallen",
  "dateLabel": "Sat 5.Oct 16:00",
  "timeline": [
    {
      "period": 1,
      "clock": "00:00",
      "teamId": null,
      "teamName": "T\u00e4by Bullcats",
      "player": "",
      "playerNumber": "",
      "score": "0-0",
      "rawType": 97,
      "side": null,
      "kind": "period",
      "label": "Start Period 1",
      "emoji": "\u23f1\ufe0f"
    },
    {
      "period": 1,
      "clock": null,
      "teamId": 1264914,
      "teamName": "Kungsholmen OG",
      "player": "Anton Jensen Wennberg",
      "playerNumber": "27",
      "score": "0-0",
      "rawType": 109,
      "side": "KOG",
      "kind": "foul",
      "label": "Personal Foul",
      "emoji": "\ud83e\udd4a"
    },
    {
      "period": 1,
      "clock": null,
      "teamId": 1264914,
      "teamName": "Kungsholmen OG",
      "player": "Anton Jensen Wennberg",
      "playerNumber": "27",
      "score": "2-0",
      "rawType": 104,
      "side": "KOG",
      "kind": "score",
      "label": "2PT Made",
      "emoji": "\ud83c\udfc0"
    },
    {
      "period": 1,
      "clock": null,
      "teamId": 1264914,
      "teamName": "Kungsholmen OG",
      "player": "Fares Cherif",
      "playerNumber": "5",
      "score": "5-0",
      "rawType": 103,
      "side": "KOG",
      "kind": "score",
      "label": "3PT Made",
      "emoji": "\ud83c\udfaf"
    },
    {
      "period": 1,
      "clock": null,
      "teamId": 1264914,
      "teamName": "Kungsholmen OG",
      "player": "Fares Cherif",
      "playerNumber": "5",
      "score": "5-0",
      "rawType": 109,
      "side": "KOG",
      "kind": "foul",
      "label": "Personal Foul",
      "emoji": "\ud83e\udd4a"
    },
    {
      "period": 1,
      "clock": null,
      "teamId": 1264914,
      "teamName": "Kungsholmen OG",
      "player": "Nicholas Frederiksen",
      "playerNumber": "36",
      "score": "7-0",
      "rawType": 104,
      "side": "KOG",
      "kind": "score",
      "label": "2PT Made",
      "emoji": "\ud83c\udfc0"
    },
    {
      "period": 1,
      "clock": null,
      "teamId": 1260452,
      "teamName": "T\u00e4by Bullcats",
      "player": "Tobias Aspeg\u00e5rdh",
      "playerNumber": "15",
      "score": "7-2",
      "rawType": 104,
      "side": "Opponent",
      "kind": "score",
      "label": "2PT Made",
      "emoji": "\ud83c\udfc0"
    },
    {
      "period": 1,
      "clock": null,
      "teamId": 1260452,
      "teamName": "T\u00e4by Bullcats",
      "player": "Christoffer Lagerstam",
      "playerNumber": "8",
      "score": "7-2",
      "rawType": 109,
      "side": "Opponent",
      "kind": "foul",
      "label": "Personal Foul",
      "emoji": "\ud83e\udd4a"
    },
    {
      "period": 1,
      "clock": null,
      "teamId": 1264914,
      "teamName": "Kungsholmen OG",
      "player": "Erik Stark",
      "playerNumber": "1",
      "score": "8-2",
      "rawType": 106,
      "side": "KOG",
      "kind": "score",
      "label": "FT Made",
      "emoji": "\ud83c\udfab"
    },
    {
      "period": 1,
      "clock": null,
      "teamId": 1264914,
      "teamName": "Kungsholmen OG",
      "player": "Erik Stark",
      "playerNumber": "1",
      "score": "9-2",
      "rawType": 106,
      "side": "KOG",
      "kind": "score",
      "label": "FT Made",
      "emoji": "\ud83c\udfab"
    },
    {
      "period": 1,
      "clock": null,
      "teamId": 1264914,
      "teamName": "Kungsholmen OG",
      "player": "Anton Jensen Wennberg",
      "playerNumber": "27",
      "score": "11-2",
      "rawType": 104,
      "side": "KOG",
      "kind": "score",
      "label": "2PT Made",
      "emoji": "\ud83c\udfc0"
    },
    {
      "period": 1,
      "clock": null,
      "teamId": 1260452,
      "teamName": "T\u00e4by Bullcats",
      "player": "Victor Silbersky",
      "playerNumber": "5",
      "score": "11-5",
      "rawType": 103,
      "side": "Opponent",
      "kind": "score",
      "label": "3PT Made",
      "emoji": "\ud83c\udfaf"
    },
    {
      "period": 1,
      "clock": null,
      "teamId": 1260452,
      "teamName": "T\u00e4by Bullcats",
      "player": "Tobias Aspeg\u00e5rdh",
      "playerNumber": "15",
      "score": "11-7",
      "rawType": 104,
      "side": "Opponent",
      "kind": "score",
      "label": "2PT Made",
      "emoji": "\ud83c\udfc0"
    },
    {
      "period": 1,
      "clock": null,
      "teamId": 1264914,
      "teamName": "Kungsholmen OG",
      "player": "Alexander Mohamud",
      "playerNumber": "6",
      "score": "13-7",
      "rawType": 104,
      "side": "KOG",
      "kind": "score",
      "label": "2PT Made",
      "emoji": "\ud83c\udfc0"
    },
    {
      "period": 1,
      "clock": null,
      "teamId": 1260452,
      "teamName": "T\u00e4by Bullcats",
      "player": "Martin B\u00f6hlin",
      "playerNumber": "12",
      "score": "13-7",
      "rawType": 109,
      "side": "Opponent",
      "kind": "foul",
      "label": "Personal Foul",
      "emoji": "\ud83e\udd4a"
    },
    {
      "period": 1,
      "clock": null,
      "teamId": 1264914,
      "teamName": "Kungsholmen OG",
      "player": "Alexander Mohamud",
      "playerNumber": "6",
      "score": "15-7",
      "rawType": 104,
      "side": "KOG",
      "kind": "score",
      "label": "2PT Made",
      "emoji": "\ud83c\udfc0"
    },
    {
      "period": 1,
      "clock": null,
      "teamId": 1260452,
      "teamName": "T\u00e4by Bullcats",
      "player": "Joakim Henriksson",
      "playerNumber": "4",
      "score": "15-9",
      "rawType": 104,
      "side": "Opponent",
      "kind": "score",
      "label": "2PT Made",
      "emoji": "\ud83c\udfc0"
    },
    {
      "period": 1,
      "clock": null,
      "teamId": 1260452,
      "teamName": "T\u00e4by Bullcats",
      "player": "Martin B\u00f6hlin",
      "playerNumber": "12",
      "score": "15-11",
      "rawType": 104,
      "side": "Opponent",
      "kind": "score",
      "label": "2PT Made",
      "emoji": "\ud83c\udfc0"
    },
    {
      "period": 1,
      "clock": null,
      "teamId": 1260452,
      "teamName": "T\u00e4by Bullcats",
      "player": "Victor By",
      "playerNumber": "13",
      "score": "15-11",
      "rawType": 109,
      "side": "Opponent",
      "kind": "foul",
      "label": "Personal Foul",
      "emoji": "\ud83e\udd4a"
    },
    {
      "period": 1,
      "clock": "10:00",
      "teamId": null,
      "teamName": "T\u00e4by Bullcats",
      "player": "",
      "playerNumber": "",
      "score": "15-11",
      "rawType": 98,
      "side": null,
      "kind": "period",
      "label": "End Period 1",
      "emoji": "\ud83d\udd14",
      "detail": "OG wins QTR 15-11, lead +4"
    },
    {
      "period": 2,
      "clock": "00:00",
      "teamId": null,
      "teamName": "T\u00e4by Bullcats",
      "player": "",
      "playerNumber": "",
      "score": "15-11",
      "rawType": 99,
      "side": null,
      "kind": "period",
      "label": "Start Period 2",
      "emoji": "\u23f1\ufe0f"
    },
    {
      "period": 2,
      "clock": null,
      "teamId": 1264914,
      "teamName": "Kungsholmen OG",
      "player": "Nicholas Frederiksen",
      "playerNumber": "36",
      "score": "17-11",
      "rawType": 104,
      "side": "KOG",
      "kind": "score",
      "label": "2PT Made",
      "emoji": "\ud83c\udfc0"
    },
    {
      "period": 2,
      "clock": null,
      "teamId": 1260452,
      "teamName": "T\u00e4by Bullcats",
      "player": "Martin B\u00f6hlin",
      "playerNumber": "12",
      "score": "17-13",
      "rawType": 104,
      "side": "Opponent",
      "kind": "score",
      "label": "2PT Made",
      "emoji": "\ud83c\udfc0"
    },
    {
      "period": 2,
      "clock": null,
      "teamId": 1260452,
      "teamName": "T\u00e4by Bullcats",
      "player": "Johan Hammarstedt",
      "playerNumber": "9",
      "score": "17-15",
      "rawType": 104,
      "side": "Opponent",
      "kind": "score",
      "label": "2PT Made",
      "emoji": "\ud83c\udfc0"
    },
    {
      "period": 2,
      "clock": null,
      "teamId": 1260452,
      "teamName": "T\u00e4by Bullcats",
      "player": "Johan Hammarstedt",
      "playerNumber": "9",
      "score": "17-15",
      "rawType": 109,
      "side": "Opponent",
      "kind": "foul",
      "label": "Personal Foul",
      "emoji": "\ud83e\udd4a"
    },
    {
      "period": 2,
      "clock": null,
      "teamId": 1264914,
      "teamName": "Kungsholmen OG",
      "player": "Nicholas Frederiksen",
      "playerNumber": "36",
      "score": "18-15",
      "rawType": 106,
      "side": "KOG",
      "kind": "score",
      "label": "FT Made",
      "emoji": "\ud83c\udfab"
    },
    {
      "period": 2,
      "clock": null,
      "teamId": 1264914,
      "teamName": "Kungsholmen OG",
      "player": "Fares Cherif",
      "playerNumber": "5",
      "score": "18-15",
      "rawType": 109,
      "side": "KOG",
      "kind": "foul",
      "label": "Personal Foul",
      "emoji": "\ud83e\udd4a"
    },
    {
      "period": 2,
      "clock": null,
      "teamId": 1264914,
      "teamName": "Kungsholmen OG",
      "player": "Fares Cherif",
      "playerNumber": "5",
      "score": "21-15",
      "rawType": 103,
      "side": "KOG",
      "kind": "score",
      "label": "3PT Made",
      "emoji": "\ud83c\udfaf"
    },
    {
      "period": 2,
      "clock": null,
      "teamId": 1264914,
      "teamName": "Kungsholmen OG",
      "player": "Fares Cherif",
      "playerNumber": "5",
      "score": "21-15",
      "rawType": 109,
      "side": "KOG",
      "kind": "foul",
      "label": "Personal Foul",
      "emoji": "\ud83e\udd4a"
    },
    {
      "period": 2,
      "clock": null,
      "teamId": 1260452,
      "teamName": "T\u00e4by Bullcats",
      "player": "Christoffer Scullman",
      "playerNumber": "14",
      "score": "21-17",
      "rawType": 104,
      "side": "Opponent",
      "kind": "score",
      "label": "2PT Made",
      "emoji": "\ud83c\udfc0"
    },
    {
      "period": 2,
      "clock": null,
      "teamId": 1264914,
      "teamName": "Kungsholmen OG",
      "player": "Nicholas Frederiksen",
      "playerNumber": "36",
      "score": "23-17",
      "rawType": 104,
      "side": "KOG",
      "kind": "score",
      "label": "2PT Made",
      "emoji": "\ud83c\udfc0"
    },
    {
      "period": 2,
      "clock": null,
      "teamId": 1260452,
      "teamName": "T\u00e4by Bullcats",
      "player": "Johan Hammarstedt",
      "playerNumber": "9",
      "score": "23-17",
      "rawType": 109,
      "side": "Opponent",
      "kind": "foul",
      "label": "Personal Foul",
      "emoji": "\ud83e\udd4a"
    },
    {
      "period": 2,
      "clock": null,
      "teamId": 1260452,
      "teamName": "T\u00e4by Bullcats",
      "player": "Tobias Aspeg\u00e5rdh",
      "playerNumber": "15",
      "score": "23-19",
      "rawType": 104,
      "side": "Opponent",
      "kind": "score",
      "label": "2PT Made",
      "emoji": "\ud83c\udfc0"
    },
    {
      "period": 2,
      "clock": null,
      "teamId": 1264914,
      "teamName": "Kungsholmen OG",
      "player": "",
      "playerNumber": "",
      "score": "23-19",
      "rawType": 108,
      "side": "KOG",
      "kind": "timeout",
      "label": "Timeout",
      "emoji": "\ud83d\uded1"
    },
    {
      "period": 2,
      "clock": null,
      "teamId": 1260452,
      "teamName": "T\u00e4by Bullcats",
      "player": "Martin B\u00f6hlin",
      "playerNumber": "12",
      "score": "23-21",
      "rawType": 104,
      "side": "Opponent",
      "kind": "score",
      "label": "2PT Made",
      "emoji": "\ud83c\udfc0"
    },
    {
      "period": 2,
      "clock": null,
      "teamId": 1264914,
      "teamName": "Kungsholmen OG",
      "player": "Anton Jensen Wennberg",
      "playerNumber": "27",
      "score": "23-21",
      "rawType": 109,
      "side": "KOG",
      "kind": "foul",
      "label": "Personal Foul",
      "emoji": "\ud83e\udd4a"
    },
    {
      "period": 2,
      "clock": null,
      "teamId": 1264914,
      "teamName": "Kungsholmen OG",
      "player": "Nicholas Frederiksen",
      "playerNumber": "36",
      "score": "25-21",
      "rawType": 104,
      "side": "KOG",
      "kind": "score",
      "label": "2PT Made",
      "emoji": "\ud83c\udfc0"
    },
    {
      "period": 2,
      "clock": null,
      "teamId": 1264914,
      "teamName": "Kungsholmen OG",
      "player": "Anton Jensen Wennberg",
      "playerNumber": "27",
      "score": "25-21",
      "rawType": 109,
      "side": "KOG",
      "kind": "foul",
      "label": "Personal Foul",
      "emoji": "\ud83e\udd4a"
    },
    {
      "period": 2,
      "clock": null,
      "teamId": 1264914,
      "teamName": "Kungsholmen OG",
      "player": "Nicholas Frederiksen",
      "playerNumber": "36",
      "score": "27-21",
      "rawType": 104,
      "side": "KOG",
      "kind": "score",
      "label": "2PT Made",
      "emoji": "\ud83c\udfc0"
    },
    {
      "period": 2,
      "clock": "10:00",
      "teamId": null,
      "teamName": "T\u00e4by Bullcats",
      "player": "",
      "playerNumber": "",
      "score": "27-21",
      "rawType": 98,
      "side": null,
      "kind": "period",
      "label": "End Period 2",
      "emoji": "\ud83d\udd14",
      "detail": "OG wins QTR 12-10, lead +6"
    },
    {
      "period": 3,
      "clock": "00:00",
      "teamId": null,
      "teamName": "T\u00e4by Bullcats",
      "player": "",
      "playerNumber": "",
      "score": "27-21",
      "rawType": 99,
      "side": null,
      "kind": "period",
      "label": "Start Period 3",
      "emoji": "\u23f1\ufe0f"
    },
    {
      "period": 3,
      "clock": null,
      "teamId": 1260452,
      "teamName": "T\u00e4by Bullcats",
      "player": "Victor Silbersky",
      "playerNumber": "5",
      "score": "27-23",
      "rawType": 104,
      "side": "Opponent",
      "kind": "score",
      "label": "2PT Made",
      "emoji": "\ud83c\udfc0"
    },
    {
      "period": 3,
      "clock": null,
      "teamId": 1260452,
      "teamName": "T\u00e4by Bullcats",
      "player": "Victor Silbersky",
      "playerNumber": "5",
      "score": "27-23",
      "rawType": 109,
      "side": "Opponent",
      "kind": "foul",
      "label": "Personal Foul",
      "emoji": "\ud83e\udd4a"
    },
    {
      "period": 3,
      "clock": null,
      "teamId": 1264914,
      "teamName": "Kungsholmen OG",
      "player": "Karl Ginsburg",
      "playerNumber": "33",
      "score": "27-23",
      "rawType": 109,
      "side": "KOG",
      "kind": "foul",
      "label": "Personal Foul",
      "emoji": "\ud83e\udd4a"
    },
    {
      "period": 3,
      "clock": null,
      "teamId": 1264914,
      "teamName": "Kungsholmen OG",
      "player": "Nicholas Frederiksen",
      "playerNumber": "36",
      "score": "27-23",
      "rawType": 109,
      "side": "KOG",
      "kind": "foul",
      "label": "Personal Foul",
      "emoji": "\ud83e\udd4a"
    },
    {
      "period": 3,
      "clock": null,
      "teamId": 1260452,
      "teamName": "T\u00e4by Bullcats",
      "player": "Johan Hammarstedt",
      "playerNumber": "9",
      "score": "27-25",
      "rawType": 104,
      "side": "Opponent",
      "kind": "score",
      "label": "2PT Made",
      "emoji": "\ud83c\udfc0"
    },
    {
      "period": 3,
      "clock": null,
      "teamId": 1264914,
      "teamName": "Kungsholmen OG",
      "player": "Mattias Malmi Pauser",
      "playerNumber": "51",
      "score": "29-25",
      "rawType": 104,
      "side": "KOG",
      "kind": "score",
      "label": "2PT Made",
      "emoji": "\ud83c\udfc0"
    },
    {
      "period": 3,
      "clock": null,
      "teamId": 1260452,
      "teamName": "T\u00e4by Bullcats",
      "player": "Johan Hammarstedt",
      "playerNumber": "9",
      "score": "29-27",
      "rawType": 104,
      "side": "Opponent",
      "kind": "score",
      "label": "2PT Made",
      "emoji": "\ud83c\udfc0"
    },
    {
      "period": 3,
      "clock": null,
      "teamId": 1260452,
      "teamName": "T\u00e4by Bullcats",
      "player": "Victor Silbersky",
      "playerNumber": "5",
      "score": "29-29",
      "rawType": 104,
      "side": "Opponent",
      "kind": "score",
      "label": "2PT Made",
      "emoji": "\ud83c\udfc0"
    },
    {
      "period": 3,
      "clock": null,
      "teamId": 1264914,
      "teamName": "Kungsholmen OG",
      "player": "Anton Jensen Wennberg",
      "playerNumber": "27",
      "score": "29-29",
      "rawType": 109,
      "side": "KOG",
      "kind": "foul",
      "label": "Personal Foul",
      "emoji": "\ud83e\udd4a"
    },
    {
      "period": 3,
      "clock": null,
      "teamId": 1264914,
      "teamName": "Kungsholmen OG",
      "player": "",
      "playerNumber": "",
      "score": "29-29",
      "rawType": 108,
      "side": "KOG",
      "kind": "timeout",
      "label": "Timeout",
      "emoji": "\ud83d\uded1"
    },
    {
      "period": 3,
      "clock": null,
      "teamId": 1264914,
      "teamName": "Kungsholmen OG",
      "player": "Mattias Malmi Pauser",
      "playerNumber": "51",
      "score": "31-29",
      "rawType": 104,
      "side": "KOG",
      "kind": "score",
      "label": "2PT Made",
      "emoji": "\ud83c\udfc0"
    },
    {
      "period": 3,
      "clock": null,
      "teamId": 1264914,
      "teamName": "Kungsholmen OG",
      "player": "Mattias Malmi Pauser",
      "playerNumber": "51",
      "score": "31-29",
      "rawType": 109,
      "side": "KOG",
      "kind": "foul",
      "label": "Personal Foul",
      "emoji": "\ud83e\udd4a"
    },
    {
      "period": 3,
      "clock": null,
      "teamId": 1264914,
      "teamName": "Kungsholmen OG",
      "player": "Nicholas Frederiksen",
      "playerNumber": "36",
      "score": "33-29",
      "rawType": 104,
      "side": "KOG",
      "kind": "score",
      "label": "2PT Made",
      "emoji": "\ud83c\udfc0"
    },
    {
      "period": 3,
      "clock": null,
      "teamId": 1260452,
      "teamName": "T\u00e4by Bullcats",
      "player": "Christoffer Lagerstam",
      "playerNumber": "8",
      "score": "33-29",
      "rawType": 109,
      "side": "Opponent",
      "kind": "foul",
      "label": "Personal Foul",
      "emoji": "\ud83e\udd4a"
    },
    {
      "period": 3,
      "clock": null,
      "teamId": 1264914,
      "teamName": "Kungsholmen OG",
      "player": "Mattias Malmi Pauser",
      "playerNumber": "51",
      "score": "35-29",
      "rawType": 104,
      "side": "KOG",
      "kind": "score",
      "label": "2PT Made",
      "emoji": "\ud83c\udfc0"
    },
    {
      "period": 3,
      "clock": null,
      "teamId": 1260452,
      "teamName": "T\u00e4by Bullcats",
      "player": "",
      "playerNumber": "",
      "score": "35-29",
      "rawType": 108,
      "side": "Opponent",
      "kind": "timeout",
      "label": "Timeout",
      "emoji": "\ud83d\uded1"
    },
    {
      "period": 3,
      "clock": null,
      "teamId": 1264914,
      "teamName": "Kungsholmen OG",
      "player": "Axel Forsberg",
      "playerNumber": "13",
      "score": "37-29",
      "rawType": 104,
      "side": "KOG",
      "kind": "score",
      "label": "2PT Made",
      "emoji": "\ud83c\udfc0"
    },
    {
      "period": 3,
      "clock": null,
      "teamId": 1260452,
      "teamName": "T\u00e4by Bullcats",
      "player": "Joakim Henriksson",
      "playerNumber": "4",
      "score": "37-29",
      "rawType": 109,
      "side": "Opponent",
      "kind": "foul",
      "label": "Personal Foul",
      "emoji": "\ud83e\udd4a"
    },
    {
      "period": 3,
      "clock": null,
      "teamId": 1264914,
      "teamName": "Kungsholmen OG",
      "player": "Erik Stark",
      "playerNumber": "1",
      "score": "38-29",
      "rawType": 106,
      "side": "KOG",
      "kind": "score",
      "label": "FT Made",
      "emoji": "\ud83c\udfab"
    },
    {
      "period": 3,
      "clock": null,
      "teamId": 1264914,
      "teamName": "Kungsholmen OG",
      "player": "Erik Stark",
      "playerNumber": "1",
      "score": "39-29",
      "rawType": 106,
      "side": "KOG",
      "kind": "score",
      "label": "FT Made",
      "emoji": "\ud83c\udfab"
    },
    {
      "period": 3,
      "clock": "10:00",
      "teamId": null,
      "teamName": "T\u00e4by Bullcats",
      "player": "",
      "playerNumber": "",
      "score": "39-29",
      "rawType": 98,
      "side": null,
      "kind": "period",
      "label": "End Period 3",
      "emoji": "\ud83d\udd14",
      "detail": "OG wins QTR 12-8, lead +10"
    },
    {
      "period": 4,
      "clock": "00:00",
      "teamId": null,
      "teamName": "T\u00e4by Bullcats",
      "player": "",
      "playerNumber": "",
      "score": "39-29",
      "rawType": 99,
      "side": null,
      "kind": "period",
      "label": "Start Period 4",
      "emoji": "\u23f1\ufe0f"
    },
    {
      "period": 4,
      "clock": null,
      "teamId": 1260452,
      "teamName": "T\u00e4by Bullcats",
      "player": "Fredrik Benckert",
      "playerNumber": "7",
      "score": "39-31",
      "rawType": 104,
      "side": "Opponent",
      "kind": "score",
      "label": "2PT Made",
      "emoji": "\ud83c\udfc0"
    },
    {
      "period": 4,
      "clock": null,
      "teamId": 1264914,
      "teamName": "Kungsholmen OG",
      "player": "Axel Forsberg",
      "playerNumber": "13",
      "score": "42-31",
      "rawType": 103,
      "side": "KOG",
      "kind": "score",
      "label": "3PT Made",
      "emoji": "\ud83c\udfaf"
    },
    {
      "period": 4,
      "clock": null,
      "teamId": 1264914,
      "teamName": "Kungsholmen OG",
      "player": "Nicholas Frederiksen",
      "playerNumber": "36",
      "score": "42-31",
      "rawType": 109,
      "side": "KOG",
      "kind": "foul",
      "label": "Personal Foul",
      "emoji": "\ud83e\udd4a"
    },
    {
      "period": 4,
      "clock": null,
      "teamId": 1264914,
      "teamName": "Kungsholmen OG",
      "player": "Erik Stark",
      "playerNumber": "1",
      "score": "42-31",
      "rawType": 109,
      "side": "KOG",
      "kind": "foul",
      "label": "Personal Foul",
      "emoji": "\ud83e\udd4a"
    },
    {
      "period": 4,
      "clock": null,
      "teamId": 1264914,
      "teamName": "Kungsholmen OG",
      "player": "Karl Ginsburg",
      "playerNumber": "33",
      "score": "42-31",
      "rawType": 109,
      "side": "KOG",
      "kind": "foul",
      "label": "Personal Foul",
      "emoji": "\ud83e\udd4a"
    },
    {
      "period": 4,
      "clock": null,
      "teamId": 1260452,
      "teamName": "T\u00e4by Bullcats",
      "player": "Tobias Aspeg\u00e5rdh",
      "playerNumber": "15",
      "score": "42-33",
      "rawType": 104,
      "side": "Opponent",
      "kind": "score",
      "label": "2PT Made",
      "emoji": "\ud83c\udfc0"
    },
    {
      "period": 4,
      "clock": null,
      "teamId": 1260452,
      "teamName": "T\u00e4by Bullcats",
      "player": "Tobias Aspeg\u00e5rdh",
      "playerNumber": "15",
      "score": "42-34",
      "rawType": 106,
      "side": "Opponent",
      "kind": "score",
      "label": "FT Made",
      "emoji": "\ud83c\udfab"
    },
    {
      "period": 4,
      "clock": null,
      "teamId": 1260452,
      "teamName": "T\u00e4by Bullcats",
      "player": "Fredrik Benckert",
      "playerNumber": "7",
      "score": "42-37",
      "rawType": 103,
      "side": "Opponent",
      "kind": "score",
      "label": "3PT Made",
      "emoji": "\ud83c\udfaf"
    },
    {
      "period": 4,
      "clock": null,
      "teamId": 1264914,
      "teamName": "Kungsholmen OG",
      "player": "Karl Ginsburg",
      "playerNumber": "33",
      "score": "44-37",
      "rawType": 104,
      "side": "KOG",
      "kind": "score",
      "label": "2PT Made",
      "emoji": "\ud83c\udfc0"
    },
    {
      "period": 4,
      "clock": null,
      "teamId": 1260452,
      "teamName": "T\u00e4by Bullcats",
      "player": "",
      "playerNumber": "",
      "score": "44-37",
      "rawType": 108,
      "side": "Opponent",
      "kind": "timeout",
      "label": "Timeout",
      "emoji": "\ud83d\uded1"
    },
    {
      "period": 4,
      "clock": null,
      "teamId": 1264914,
      "teamName": "Kungsholmen OG",
      "player": "Alexander Mohamud",
      "playerNumber": "6",
      "score": "46-37",
      "rawType": 104,
      "side": "KOG",
      "kind": "score",
      "label": "2PT Made",
      "emoji": "\ud83c\udfc0"
    },
    {
      "period": 4,
      "clock": null,
      "teamId": 1260452,
      "teamName": "T\u00e4by Bullcats",
      "player": "Christoffer Lagerstam",
      "playerNumber": "8",
      "score": "46-39",
      "rawType": 104,
      "side": "Opponent",
      "kind": "score",
      "label": "2PT Made",
      "emoji": "\ud83c\udfc0"
    },
    {
      "period": 4,
      "clock": null,
      "teamId": 1260452,
      "teamName": "T\u00e4by Bullcats",
      "player": "Victor Silbersky",
      "playerNumber": "5",
      "score": "46-42",
      "rawType": 103,
      "side": "Opponent",
      "kind": "score",
      "label": "3PT Made",
      "emoji": "\ud83c\udfaf"
    },
    {
      "period": 4,
      "clock": null,
      "teamId": 1260452,
      "teamName": "T\u00e4by Bullcats",
      "player": "Christoffer Lagerstam",
      "playerNumber": "8",
      "score": "46-42",
      "rawType": 109,
      "side": "Opponent",
      "kind": "foul",
      "label": "Personal Foul",
      "emoji": "\ud83e\udd4a"
    },
    {
      "period": 4,
      "clock": null,
      "teamId": 1264914,
      "teamName": "Kungsholmen OG",
      "player": "Mattias Malmi Pauser",
      "playerNumber": "51",
      "score": "48-42",
      "rawType": 104,
      "side": "KOG",
      "kind": "score",
      "label": "2PT Made",
      "emoji": "\ud83c\udfc0"
    },
    {
      "period": 4,
      "clock": null,
      "teamId": 1264914,
      "teamName": "Kungsholmen OG",
      "player": "Nicholas Frederiksen",
      "playerNumber": "36",
      "score": "48-42",
      "rawType": 109,
      "side": "KOG",
      "kind": "foul",
      "label": "Personal Foul",
      "emoji": "\ud83e\udd4a"
    },
    {
      "period": 4,
      "clock": null,
      "teamId": 1264914,
      "teamName": "Kungsholmen OG",
      "player": "Alexander Mohamud",
      "playerNumber": "6",
      "score": "48-42",
      "rawType": 109,
      "side": "KOG",
      "kind": "foul",
      "label": "Personal Foul",
      "emoji": "\ud83e\udd4a"
    },
    {
      "period": 4,
      "clock": null,
      "teamId": 1264914,
      "teamName": "Kungsholmen OG",
      "player": "Axel Forsberg",
      "playerNumber": "13",
      "score": "51-42",
      "rawType": 103,
      "side": "KOG",
      "kind": "score",
      "label": "3PT Made",
      "emoji": "\ud83c\udfaf"
    },
    {
      "period": 4,
      "clock": null,
      "teamId": 1264914,
      "teamName": "Kungsholmen OG",
      "player": "Mattias Malmi Pauser",
      "playerNumber": "51",
      "score": "51-42",
      "rawType": 109,
      "side": "KOG",
      "kind": "foul",
      "label": "Personal Foul",
      "emoji": "\ud83e\udd4a"
    },
    {
      "period": 4,
      "clock": null,
      "teamId": 1260452,
      "teamName": "T\u00e4by Bullcats",
      "player": "Tobias Aspeg\u00e5rdh",
      "playerNumber": "15",
      "score": "51-43",
      "rawType": 106,
      "side": "Opponent",
      "kind": "score",
      "label": "FT Made",
      "emoji": "\ud83c\udfab"
    },
    {
      "period": 4,
      "clock": null,
      "teamId": 1260452,
      "teamName": "T\u00e4by Bullcats",
      "player": "Tobias Aspeg\u00e5rdh",
      "playerNumber": "15",
      "score": "51-44",
      "rawType": 106,
      "side": "Opponent",
      "kind": "score",
      "label": "FT Made",
      "emoji": "\ud83c\udfab"
    },
    {
      "period": 4,
      "clock": null,
      "teamId": 1260452,
      "teamName": "T\u00e4by Bullcats",
      "player": "Tobias Aspeg\u00e5rdh",
      "playerNumber": "15",
      "score": "51-46",
      "rawType": 104,
      "side": "Opponent",
      "kind": "score",
      "label": "2PT Made",
      "emoji": "\ud83c\udfc0"
    },
    {
      "period": 4,
      "clock": null,
      "teamId": 1264914,
      "teamName": "Kungsholmen OG",
      "player": "Mattias Malmi Pauser",
      "playerNumber": "51",
      "score": "53-46",
      "rawType": 104,
      "side": "KOG",
      "kind": "score",
      "label": "2PT Made",
      "emoji": "\ud83c\udfc0"
    },
    {
      "period": 4,
      "clock": null,
      "teamId": 1260452,
      "teamName": "T\u00e4by Bullcats",
      "player": "Martin B\u00f6hlin",
      "playerNumber": "12",
      "score": "53-49",
      "rawType": 103,
      "side": "Opponent",
      "kind": "score",
      "label": "3PT Made",
      "emoji": "\ud83c\udfaf"
    },
    {
      "period": 4,
      "clock": null,
      "teamId": 1264914,
      "teamName": "Kungsholmen OG",
      "player": "Anton Jensen Wennberg",
      "playerNumber": "27",
      "score": "53-49",
      "rawType": 109,
      "side": "KOG",
      "kind": "foul",
      "label": "Personal Foul",
      "emoji": "\ud83e\udd4a"
    },
    {
      "period": 4,
      "clock": null,
      "teamId": 1260452,
      "teamName": "T\u00e4by Bullcats",
      "player": "Christoffer Lagerstam",
      "playerNumber": "8",
      "score": "53-51",
      "rawType": 104,
      "side": "Opponent",
      "kind": "score",
      "label": "2PT Made",
      "emoji": "\ud83c\udfc0"
    },
    {
      "period": 4,
      "clock": null,
      "teamId": 1264914,
      "teamName": "Kungsholmen OG",
      "player": "",
      "playerNumber": "",
      "score": "53-51",
      "rawType": 108,
      "side": "KOG",
      "kind": "timeout",
      "label": "Timeout",
      "emoji": "\ud83d\uded1"
    },
    {
      "period": 4,
      "clock": null,
      "teamId": 1260452,
      "teamName": "T\u00e4by Bullcats",
      "player": "Christoffer Scullman",
      "playerNumber": "14",
      "score": "53-51",
      "rawType": 109,
      "side": "Opponent",
      "kind": "foul",
      "label": "Personal Foul",
      "emoji": "\ud83e\udd4a"
    },
    {
      "period": 4,
      "clock": null,
      "teamId": 1264914,
      "teamName": "Kungsholmen OG",
      "player": "Erik Stark",
      "playerNumber": "1",
      "score": "53-51",
      "rawType": 109,
      "side": "KOG",
      "kind": "foul",
      "label": "Personal Foul",
      "emoji": "\ud83e\udd4a"
    },
    {
      "period": 4,
      "clock": "10:00",
      "teamId": null,
      "teamName": "T\u00e4by Bullcats",
      "player": "",
      "playerNumber": "",
      "score": "53-51",
      "rawType": 100,
      "side": null,
      "kind": "period",
      "label": "End Period 4",
      "emoji": "\ud83d\udd14",
      "detail": "T\u00e4by Bullcats wins QTR 22-14, lead +2"
    },
    {
      "period": 4,
      "clock": "10:00",
      "teamId": null,
      "teamName": "T\u00e4by Bullcats",
      "player": "",
      "playerNumber": "",
      "score": "53-51",
      "rawType": 100,
      "side": "KOG",
      "kind": "period",
      "label": "Final Buzzer \u2014 Kungsholmen OG",
      "emoji": "\ud83c\udfc1"
    }
  ]
}