{
  "matchId": 31909647,
  "opponent": "Duga",
  "homeOrAway": "away",
  "location": "Enskedehallen L",
  "dateLabel": "Sun 12.Jan 13:45",
  "timeline": [
    {
      "period": 1,
      "clock": "00:00",
      "teamId": null,
      "teamName": "Duga",
      "player": "",
      "playerNumber": "",
      "score": "0-0",
      "rawType": 97,
      "side": null,
      "kind": "period",
      "label": "Start Period 1",
      "emoji": "\u23f1\ufe0f"
    },
    {
      "period": 1,
      "clock": null,
      "teamId": 1264914,
      "teamName": "Kungsholmen OG",
      "player": "Erik Stark",
      "playerNumber": "1",
      "score": "2-0",
      "rawType": 104,
      "side": "KOG",
      "kind": "score",
      "label": "2PT Made",
      "emoji": "\ud83c\udfc0"
    },
    {
      "period": 1,
      "clock": null,
      "teamId": 1268171,
      "teamName": "Duga",
      "player": "Simon \u00c5kerlund",
      "playerNumber": "5",
      "score": "2-2",
      "rawType": 104,
      "side": "Opponent",
      "kind": "score",
      "label": "2PT Made",
      "emoji": "\ud83c\udfc0"
    },
    {
      "period": 1,
      "clock": null,
      "teamId": 1264914,
      "teamName": "Kungsholmen OG",
      "player": "Niklas Walles",
      "playerNumber": "3",
      "score": "4-2",
      "rawType": 104,
      "side": "KOG",
      "kind": "score",
      "label": "2PT Made",
      "emoji": "\ud83c\udfc0"
    },
    {
      "period": 1,
      "clock": null,
      "teamId": 1264914,
      "teamName": "Kungsholmen OG",
      "player": "Nicholas Frederiksen",
      "playerNumber": "36",
      "score": "6-2",
      "rawType": 104,
      "side": "KOG",
      "kind": "score",
      "label": "2PT Made",
      "emoji": "\ud83c\udfc0"
    },
    {
      "period": 1,
      "clock": null,
      "teamId": 1268171,
      "teamName": "Duga",
      "player": "Fredrik Skogsj\u00f6",
      "playerNumber": "",
      "score": "6-5",
      "rawType": 103,
      "side": "Opponent",
      "kind": "score",
      "label": "3PT Made",
      "emoji": "\ud83c\udfaf"
    },
    {
      "period": 1,
      "clock": null,
      "teamId": 1268171,
      "teamName": "Duga",
      "player": "Anton Andersson Andrejic",
      "playerNumber": "55",
      "score": "6-5",
      "rawType": 109,
      "side": "Opponent",
      "kind": "foul",
      "label": "Personal Foul",
      "emoji": "\ud83e\udd4a"
    },
    {
      "period": 1,
      "clock": null,
      "teamId": 1264914,
      "teamName": "Kungsholmen OG",
      "player": "Nicholas Frederiksen",
      "playerNumber": "36",
      "score": "7-5",
      "rawType": 106,
      "side": "KOG",
      "kind": "score",
      "label": "FT Made",
      "emoji": "\ud83c\udfab"
    },
    {
      "period": 1,
      "clock": null,
      "teamId": 1264914,
      "teamName": "Kungsholmen OG",
      "player": "Nicholas Frederiksen",
      "playerNumber": "36",
      "score": "8-5",
      "rawType": 106,
      "side": "KOG",
      "kind": "score",
      "label": "FT Made",
      "emoji": "\ud83c\udfab"
    },
    {
      "period": 1,
      "clock": null,
      "teamId": 1264914,
      "teamName": "Kungsholmen OG",
      "player": "Niklas Walles",
      "playerNumber": "3",
      "score": "10-5",
      "rawType": 104,
      "side": "KOG",
      "kind": "score",
      "label": "2PT Made",
      "emoji": "\ud83c\udfc0"
    },
    {
      "period": 1,
      "clock": null,
      "teamId": 1264914,
      "teamName": "Kungsholmen OG",
      "player": "Niklas Walles",
      "playerNumber": "3",
      "score": "12-5",
      "rawType": 104,
      "side": "KOG",
      "kind": "score",
      "label": "2PT Made",
      "emoji": "\ud83c\udfc0"
    },
    {
      "period": 1,
      "clock": null,
      "teamId": 1268171,
      "teamName": "Duga",
      "player": "Fredrik Skogsj\u00f6",
      "playerNumber": "",
      "score": "12-7",
      "rawType": 104,
      "side": "Opponent",
      "kind": "score",
      "label": "2PT Made",
      "emoji": "\ud83c\udfc0"
    },
    {
      "period": 1,
      "clock": null,
      "teamId": 1268171,
      "teamName": "Duga",
      "player": "Simon \u00c5kerlund",
      "playerNumber": "5",
      "score": "12-7",
      "rawType": 109,
      "side": "Opponent",
      "kind": "foul",
      "label": "Personal Foul",
      "emoji": "\ud83e\udd4a"
    },
    {
      "period": 1,
      "clock": null,
      "teamId": 1268171,
      "teamName": "Duga",
      "player": "Lucas Rudqwist",
      "playerNumber": "9",
      "score": "12-9",
      "rawType": 104,
      "side": "Opponent",
      "kind": "score",
      "label": "2PT Made",
      "emoji": "\ud83c\udfc0"
    },
    {
      "period": 1,
      "clock": null,
      "teamId": 1264914,
      "teamName": "Kungsholmen OG",
      "player": "Niklas Walles",
      "playerNumber": "3",
      "score": "12-9",
      "rawType": 109,
      "side": "KOG",
      "kind": "foul",
      "label": "Personal Foul",
      "emoji": "\ud83e\udd4a"
    },
    {
      "period": 1,
      "clock": null,
      "teamId": 1264914,
      "teamName": "Kungsholmen OG",
      "player": "Anton Jensen Wennberg",
      "playerNumber": "27",
      "score": "12-9",
      "rawType": 109,
      "side": "KOG",
      "kind": "foul",
      "label": "Personal Foul",
      "emoji": "\ud83e\udd4a"
    },
    {
      "period": 1,
      "clock": null,
      "teamId": 1268171,
      "teamName": "Duga",
      "player": "Andreas Skarfors",
      "playerNumber": "30",
      "score": "12-11",
      "rawType": 104,
      "side": "Opponent",
      "kind": "score",
      "label": "2PT Made",
      "emoji": "\ud83c\udfc0"
    },
    {
      "period": 1,
      "clock": null,
      "teamId": 1268171,
      "teamName": "Duga",
      "player": "Axel Blomgren",
      "playerNumber": "1",
      "score": "12-11",
      "rawType": 109,
      "side": "Opponent",
      "kind": "foul",
      "label": "Personal Foul",
      "emoji": "\ud83e\udd4a"
    },
    {
      "period": 1,
      "clock": null,
      "teamId": 1268171,
      "teamName": "Duga",
      "player": "Arvid Iverstam",
      "playerNumber": "88",
      "score": "12-13",
      "rawType": 104,
      "side": "Opponent",
      "kind": "score",
      "label": "2PT Made",
      "emoji": "\ud83c\udfc0"
    },
    {
      "period": 1,
      "clock": null,
      "teamId": 1268171,
      "teamName": "Duga",
      "player": "Axel Blomgren",
      "playerNumber": "1",
      "score": "12-15",
      "rawType": 104,
      "side": "Opponent",
      "kind": "score",
      "label": "2PT Made",
      "emoji": "\ud83c\udfc0"
    },
    {
      "period": 1,
      "clock": null,
      "teamId": 1268171,
      "teamName": "Duga",
      "player": "Arvid Iverstam",
      "playerNumber": "88",
      "score": "12-15",
      "rawType": 109,
      "side": "Opponent",
      "kind": "foul",
      "label": "Personal Foul",
      "emoji": "\ud83e\udd4a"
    },
    {
      "period": 1,
      "clock": "10:00",
      "teamId": null,
      "teamName": "Duga",
      "player": "",
      "playerNumber": "",
      "score": "12-15",
      "rawType": 98,
      "side": null,
      "kind": "period",
      "label": "End Period 1",
      "emoji": "\ud83d\udd14",
      "detail": "Duga wins QTR 15-12, lead -3"
    },
    {
      "period": 2,
      "clock": "00:00",
      "teamId": null,
      "teamName": "Duga",
      "player": "",
      "playerNumber": "",
      "score": "12-15",
      "rawType": 99,
      "side": null,
      "kind": "period",
      "label": "Start Period 2",
      "emoji": "\u23f1\ufe0f"
    },
    {
      "period": 2,
      "clock": null,
      "teamId": 1264914,
      "teamName": "Kungsholmen OG",
      "player": "Nicholas Frederiksen",
      "playerNumber": "36",
      "score": "12-15",
      "rawType": 109,
      "side": "KOG",
      "kind": "foul",
      "label": "Personal Foul",
      "emoji": "\ud83e\udd4a"
    },
    {
      "period": 2,
      "clock": null,
      "teamId": 1264914,
      "teamName": "Kungsholmen OG",
      "player": "Anton Jensen Wennberg",
      "playerNumber": "27",
      "score": "12-15",
      "rawType": 109,
      "side": "KOG",
      "kind": "foul",
      "label": "Personal Foul",
      "emoji": "\ud83e\udd4a"
    },
    {
      "period": 2,
      "clock": null,
      "teamId": 1268171,
      "teamName": "Duga",
      "player": "Lucas Rudqwist",
      "playerNumber": "9",
      "score": "12-15",
      "rawType": 109,
      "side": "Opponent",
      "kind": "foul",
      "label": "Personal Foul",
      "emoji": "\ud83e\udd4a"
    },
    {
      "period": 2,
      "clock": null,
      "teamId": 1264914,
      "teamName": "Kungsholmen OG",
      "player": "Niklas Walles",
      "playerNumber": "3",
      "score": "13-15",
      "rawType": 106,
      "side": "KOG",
      "kind": "score",
      "label": "FT Made",
      "emoji": "\ud83c\udfab"
    },
    {
      "period": 2,
      "clock": null,
      "teamId": 1268171,
      "teamName": "Duga",
      "player": "Fredrik Skogsj\u00f6",
      "playerNumber": "",
      "score": "13-15",
      "rawType": 109,
      "side": "Opponent",
      "kind": "foul",
      "label": "Personal Foul",
      "emoji": "\ud83e\udd4a"
    },
    {
      "period": 2,
      "clock": null,
      "teamId": 1264914,
      "teamName": "Kungsholmen OG",
      "player": "Anton Jensen Wennberg",
      "playerNumber": "27",
      "score": "14-15",
      "rawType": 106,
      "side": "KOG",
      "kind": "score",
      "label": "FT Made",
      "emoji": "\ud83c\udfab"
    },
    {
      "period": 2,
      "clock": null,
      "teamId": 1264914,
      "teamName": "Kungsholmen OG",
      "player": "Anton Jensen Wennberg",
      "playerNumber": "27",
      "score": "14-15",
      "rawType": 109,
      "side": "KOG",
      "kind": "foul",
      "label": "Personal Foul",
      "emoji": "\ud83e\udd4a"
    },
    {
      "period": 2,
      "clock": null,
      "teamId": 1268171,
      "teamName": "Duga",
      "player": "Fredrik Skogsj\u00f6",
      "playerNumber": "",
      "score": "14-17",
      "rawType": 104,
      "side": "Opponent",
      "kind": "score",
      "label": "2PT Made",
      "emoji": "\ud83c\udfc0"
    },
    {
      "period": 2,
      "clock": null,
      "teamId": 1268171,
      "teamName": "Duga",
      "player": "Fredrik Skogsj\u00f6",
      "playerNumber": "",
      "score": "14-19",
      "rawType": 104,
      "side": "Opponent",
      "kind": "score",
      "label": "2PT Made",
      "emoji": "\ud83c\udfc0"
    },
    {
      "period": 2,
      "clock": null,
      "teamId": 1264914,
      "teamName": "Kungsholmen OG",
      "player": "Erik Stark",
      "playerNumber": "1",
      "score": "14-19",
      "rawType": 109,
      "side": "KOG",
      "kind": "foul",
      "label": "Personal Foul",
      "emoji": "\ud83e\udd4a"
    },
    {
      "period": 2,
      "clock": null,
      "teamId": 1268171,
      "teamName": "Duga",
      "player": "Simon \u00c5kerlund",
      "playerNumber": "5",
      "score": "14-20",
      "rawType": 106,
      "side": "Opponent",
      "kind": "score",
      "label": "FT Made",
      "emoji": "\ud83c\udfab"
    },
    {
      "period": 2,
      "clock": null,
      "teamId": 1264914,
      "teamName": "Kungsholmen OG",
      "player": "Nicholas Frederiksen",
      "playerNumber": "36",
      "score": "16-20",
      "rawType": 104,
      "side": "KOG",
      "kind": "score",
      "label": "2PT Made",
      "emoji": "\ud83c\udfc0"
    },
    {
      "period": 2,
      "clock": null,
      "teamId": 1268171,
      "teamName": "Duga",
      "player": "Simon \u00c5kerlund",
      "playerNumber": "5",
      "score": "16-22",
      "rawType": 104,
      "side": "Opponent",
      "kind": "score",
      "label": "2PT Made",
      "emoji": "\ud83c\udfc0"
    },
    {
      "period": 2,
      "clock": null,
      "teamId": 1268171,
      "teamName": "Duga",
      "player": "Andreas Skarfors",
      "playerNumber": "30",
      "score": "16-22",
      "rawType": 109,
      "side": "Opponent",
      "kind": "foul",
      "label": "Personal Foul",
      "emoji": "\ud83e\udd4a"
    },
    {
      "period": 2,
      "clock": null,
      "teamId": 1264914,
      "teamName": "Kungsholmen OG",
      "player": "Niklas Walles",
      "playerNumber": "3",
      "score": "18-22",
      "rawType": 104,
      "side": "KOG",
      "kind": "score",
      "label": "2PT Made",
      "emoji": "\ud83c\udfc0"
    },
    {
      "period": 2,
      "clock": null,
      "teamId": 1264914,
      "teamName": "Kungsholmen OG",
      "player": "Erik Stark",
      "playerNumber": "1",
      "score": "20-22",
      "rawType": 104,
      "side": "KOG",
      "kind": "score",
      "label": "2PT Made",
      "emoji": "\ud83c\udfc0"
    },
    {
      "period": 2,
      "clock": null,
      "teamId": 1264914,
      "teamName": "Kungsholmen OG",
      "player": "Niklas Walles",
      "playerNumber": "3",
      "score": "20-22",
      "rawType": 109,
      "side": "KOG",
      "kind": "foul",
      "label": "Personal Foul",
      "emoji": "\ud83e\udd4a"
    },
    {
      "period": 2,
      "clock": null,
      "teamId": 1268171,
      "teamName": "Duga",
      "player": "Andreas Skarfors",
      "playerNumber": "30",
      "score": "20-23",
      "rawType": 106,
      "side": "Opponent",
      "kind": "score",
      "label": "FT Made",
      "emoji": "\ud83c\udfab"
    },
    {
      "period": 2,
      "clock": null,
      "teamId": 1264914,
      "teamName": "Kungsholmen OG",
      "player": "Joakim Walles",
      "playerNumber": "15",
      "score": "22-23",
      "rawType": 104,
      "side": "KOG",
      "kind": "score",
      "label": "2PT Made",
      "emoji": "\ud83c\udfc0"
    },
    {
      "period": 2,
      "clock": null,
      "teamId": 1268171,
      "teamName": "Duga",
      "player": "Simon \u00c5kerlund",
      "playerNumber": "5",
      "score": "22-25",
      "rawType": 104,
      "side": "Opponent",
      "kind": "score",
      "label": "2PT Made",
      "emoji": "\ud83c\udfc0"
    },
    {
      "period": 2,
      "clock": null,
      "teamId": 1264914,
      "teamName": "Kungsholmen OG",
      "player": "Fares Cherif",
      "playerNumber": "5",
      "score": "24-25",
      "rawType": 104,
      "side": "KOG",
      "kind": "score",
      "label": "2PT Made",
      "emoji": "\ud83c\udfc0"
    },
    {
      "period": 2,
      "clock": null,
      "teamId": 1268171,
      "teamName": "Duga",
      "player": "Simon \u00c5kerlund",
      "playerNumber": "5",
      "score": "24-25",
      "rawType": 109,
      "side": "Opponent",
      "kind": "foul",
      "label": "Personal Foul",
      "emoji": "\ud83e\udd4a"
    },
    {
      "period": 2,
      "clock": null,
      "teamId": 1264914,
      "teamName": "Kungsholmen OG",
      "player": "Fares Cherif",
      "playerNumber": "5",
      "score": "24-25",
      "rawType": 109,
      "side": "KOG",
      "kind": "foul",
      "label": "Personal Foul",
      "emoji": "\ud83e\udd4a"
    },
    {
      "period": 2,
      "clock": null,
      "teamId": 1268171,
      "teamName": "Duga",
      "player": "Arvid Iverstam",
      "playerNumber": "88",
      "score": "24-26",
      "rawType": 106,
      "side": "Opponent",
      "kind": "score",
      "label": "FT Made",
      "emoji": "\ud83c\udfab"
    },
    {
      "period": 2,
      "clock": null,
      "teamId": 1268171,
      "teamName": "Duga",
      "player": "Arvid Iverstam",
      "playerNumber": "88",
      "score": "24-27",
      "rawType": 106,
      "side": "Opponent",
      "kind": "score",
      "label": "FT Made",
      "emoji": "\ud83c\udfab"
    },
    {
      "period": 2,
      "clock": null,
      "teamId": 1264914,
      "teamName": "Kungsholmen OG",
      "player": "Nicholas Frederiksen",
      "playerNumber": "36",
      "score": "26-27",
      "rawType": 104,
      "side": "KOG",
      "kind": "score",
      "label": "2PT Made",
      "emoji": "\ud83c\udfc0"
    },
    {
      "period": 2,
      "clock": null,
      "teamId": 1264914,
      "teamName": "Kungsholmen OG",
      "player": "Joakim Walles",
      "playerNumber": "15",
      "score": "26-27",
      "rawType": 109,
      "side": "KOG",
      "kind": "foul",
      "label": "Personal Foul",
      "emoji": "\ud83e\udd4a"
    },
    {
      "period": 2,
      "clock": null,
      "teamId": 1264914,
      "teamName": "Kungsholmen OG",
      "player": "Joakim Walles",
      "playerNumber": "15",
      "score": "28-27",
      "rawType": 104,
      "side": "KOG",
      "kind": "score",
      "label": "2PT Made",
      "emoji": "\ud83c\udfc0"
    },
    {
      "period": 2,
      "clock": "10:00",
      "teamId": null,
      "teamName": "Duga",
      "player": "",
      "playerNumber": "",
      "score": "28-27",
      "rawType": 98,
      "side": null,
      "kind": "period",
      "label": "End Period 2",
      "emoji": "\ud83d\udd14",
      "detail": "OG wins QTR 16-12, lead +1"
    },
    {
      "period": 3,
      "clock": "00:00",
      "teamId": null,
      "teamName": "Duga",
      "player": "",
      "playerNumber": "",
      "score": "28-27",
      "rawType": 99,
      "side": null,
      "kind": "period",
      "label": "Start Period 3",
      "emoji": "\u23f1\ufe0f"
    },
    {
      "period": 3,
      "clock": null,
      "teamId": 1268171,
      "teamName": "Duga",
      "player": "Fredrik Skogsj\u00f6",
      "playerNumber": "",
      "score": "28-29",
      "rawType": 104,
      "side": "Opponent",
      "kind": "score",
      "label": "2PT Made",
      "emoji": "\ud83c\udfc0"
    },
    {
      "period": 3,
      "clock": null,
      "teamId": 1264914,
      "teamName": "Kungsholmen OG",
      "player": "Anton Jensen Wennberg",
      "playerNumber": "27",
      "score": "28-29",
      "rawType": 109,
      "side": "KOG",
      "kind": "foul",
      "label": "Personal Foul",
      "emoji": "\ud83e\udd4a"
    },
    {
      "period": 3,
      "clock": null,
      "teamId": 1268171,
      "teamName": "Duga",
      "player": "Anton Andersson Andrejic",
      "playerNumber": "55",
      "score": "28-30",
      "rawType": 106,
      "side": "Opponent",
      "kind": "score",
      "label": "FT Made",
      "emoji": "\ud83c\udfab"
    },
    {
      "period": 3,
      "clock": null,
      "teamId": 1268171,
      "teamName": "Duga",
      "player": "Anton Andersson Andrejic",
      "playerNumber": "55",
      "score": "28-30",
      "rawType": 109,
      "side": "Opponent",
      "kind": "foul",
      "label": "Personal Foul",
      "emoji": "\ud83e\udd4a"
    },
    {
      "period": 3,
      "clock": null,
      "teamId": 1264914,
      "teamName": "Kungsholmen OG",
      "player": "Axel Forsberg",
      "playerNumber": "13",
      "score": "30-30",
      "rawType": 104,
      "side": "KOG",
      "kind": "score",
      "label": "2PT Made",
      "emoji": "\ud83c\udfc0"
    },
    {
      "period": 3,
      "clock": null,
      "teamId": 1268171,
      "teamName": "Duga",
      "player": "Fredrik Skogsj\u00f6",
      "playerNumber": "",
      "score": "30-32",
      "rawType": 104,
      "side": "Opponent",
      "kind": "score",
      "label": "2PT Made",
      "emoji": "\ud83c\udfc0"
    },
    {
      "period": 3,
      "clock": null,
      "teamId": 1268171,
      "teamName": "Duga",
      "player": "Fredrik Skogsj\u00f6",
      "playerNumber": "",
      "score": "30-35",
      "rawType": 103,
      "side": "Opponent",
      "kind": "score",
      "label": "3PT Made",
      "emoji": "\ud83c\udfaf"
    },
    {
      "period": 3,
      "clock": null,
      "teamId": 1268171,
      "teamName": "Duga",
      "player": "Fredrik Skogsj\u00f6",
      "playerNumber": "",
      "score": "30-38",
      "rawType": 103,
      "side": "Opponent",
      "kind": "score",
      "label": "3PT Made",
      "emoji": "\ud83c\udfaf"
    },
    {
      "period": 3,
      "clock": null,
      "teamId": 1264914,
      "teamName": "Kungsholmen OG",
      "player": "Erik Stark",
      "playerNumber": "1",
      "score": "32-38",
      "rawType": 104,
      "side": "KOG",
      "kind": "score",
      "label": "2PT Made",
      "emoji": "\ud83c\udfc0"
    },
    {
      "period": 3,
      "clock": null,
      "teamId": 1264914,
      "teamName": "Kungsholmen OG",
      "player": "Joakim Walles",
      "playerNumber": "15",
      "score": "34-38",
      "rawType": 104,
      "side": "KOG",
      "kind": "score",
      "label": "2PT Made",
      "emoji": "\ud83c\udfc0"
    },
    {
      "period": 3,
      "clock": null,
      "teamId": 1268171,
      "teamName": "Duga",
      "player": "Anton Andersson Andrejic",
      "playerNumber": "55",
      "score": "34-41",
      "rawType": 103,
      "side": "Opponent",
      "kind": "score",
      "label": "3PT Made",
      "emoji": "\ud83c\udfaf"
    },
    {
      "period": 3,
      "clock": null,
      "teamId": 1264914,
      "teamName": "Kungsholmen OG",
      "player": "Nicholas Frederiksen",
      "playerNumber": "36",
      "score": "34-41",
      "rawType": 109,
      "side": "KOG",
      "kind": "foul",
      "label": "Personal Foul",
      "emoji": "\ud83e\udd4a"
    },
    {
      "period": 3,
      "clock": null,
      "teamId": 1268171,
      "teamName": "Duga",
      "player": "Simon \u00c5kerlund",
      "playerNumber": "5",
      "score": "34-42",
      "rawType": 106,
      "side": "Opponent",
      "kind": "score",
      "label": "FT Made",
      "emoji": "\ud83c\udfab"
    },
    {
      "period": 3,
      "clock": null,
      "teamId": 1268171,
      "teamName": "Duga",
      "player": "Simon \u00c5kerlund",
      "playerNumber": "5",
      "score": "34-43",
      "rawType": 106,
      "side": "Opponent",
      "kind": "score",
      "label": "FT Made",
      "emoji": "\ud83c\udfab"
    },
    {
      "period": 3,
      "clock": null,
      "teamId": 1268171,
      "teamName": "Duga",
      "player": "Andreas Skarfors",
      "playerNumber": "30",
      "score": "34-45",
      "rawType": 104,
      "side": "Opponent",
      "kind": "score",
      "label": "2PT Made",
      "emoji": "\ud83c\udfc0"
    },
    {
      "period": 3,
      "clock": null,
      "teamId": 1264914,
      "teamName": "Kungsholmen OG",
      "player": "",
      "playerNumber": "",
      "score": "34-45",
      "rawType": 108,
      "side": "KOG",
      "kind": "timeout",
      "label": "Timeout",
      "emoji": "\ud83d\uded1"
    },
    {
      "period": 3,
      "clock": null,
      "teamId": 1264914,
      "teamName": "Kungsholmen OG",
      "player": "Erik Stark",
      "playerNumber": "1",
      "score": "34-45",
      "rawType": 109,
      "side": "KOG",
      "kind": "foul",
      "label": "Personal Foul",
      "emoji": "\ud83e\udd4a"
    },
    {
      "period": 3,
      "clock": null,
      "teamId": 1268171,
      "teamName": "Duga",
      "player": "Arvid Iverstam",
      "playerNumber": "88",
      "score": "34-46",
      "rawType": 106,
      "side": "Opponent",
      "kind": "score",
      "label": "FT Made",
      "emoji": "\ud83c\udfab"
    },
    {
      "period": 3,
      "clock": null,
      "teamId": 1268171,
      "teamName": "Duga",
      "player": "Lucas Rudqwist",
      "playerNumber": "9",
      "score": "34-46",
      "rawType": 109,
      "side": "Opponent",
      "kind": "foul",
      "label": "Personal Foul",
      "emoji": "\ud83e\udd4a"
    },
    {
      "period": 3,
      "clock": null,
      "teamId": 1264914,
      "teamName": "Kungsholmen OG",
      "player": "Erik Stark",
      "playerNumber": "1",
      "score": "34-46",
      "rawType": 109,
      "side": "KOG",
      "kind": "foul",
      "label": "Personal Foul",
      "emoji": "\ud83e\udd4a"
    },
    {
      "period": 3,
      "clock": null,
      "teamId": 1268171,
      "teamName": "Duga",
      "player": "Arvid Iverstam",
      "playerNumber": "88",
      "score": "34-48",
      "rawType": 104,
      "side": "Opponent",
      "kind": "score",
      "label": "2PT Made",
      "emoji": "\ud83c\udfc0"
    },
    {
      "period": 3,
      "clock": null,
      "teamId": 1268171,
      "teamName": "Duga",
      "player": "Andreas Skarfors",
      "playerNumber": "30",
      "score": "34-50",
      "rawType": 104,
      "side": "Opponent",
      "kind": "score",
      "label": "2PT Made",
      "emoji": "\ud83c\udfc0"
    },
    {
      "period": 3,
      "clock": null,
      "teamId": 1264914,
      "teamName": "Kungsholmen OG",
      "player": "Joakim Walles",
      "playerNumber": "15",
      "score": "35-50",
      "rawType": 106,
      "side": "KOG",
      "kind": "score",
      "label": "FT Made",
      "emoji": "\ud83c\udfab"
    },
    {
      "period": 3,
      "clock": null,
      "teamId": 1268171,
      "teamName": "Duga",
      "player": "Arvid Iverstam",
      "playerNumber": "88",
      "score": "35-52",
      "rawType": 104,
      "side": "Opponent",
      "kind": "score",
      "label": "2PT Made",
      "emoji": "\ud83c\udfc0"
    },
    {
      "period": 3,
      "clock": null,
      "teamId": 1268171,
      "teamName": "Duga",
      "player": "Fredrik Skogsj\u00f6",
      "playerNumber": "",
      "score": "35-52",
      "rawType": 109,
      "side": "Opponent",
      "kind": "foul",
      "label": "Personal Foul",
      "emoji": "\ud83e\udd4a"
    },
    {
      "period": 3,
      "clock": null,
      "teamId": 1268171,
      "teamName": "Duga",
      "player": "Simon \u00c5kerlund",
      "playerNumber": "5",
      "score": "35-54",
      "rawType": 104,
      "side": "Opponent",
      "kind": "score",
      "label": "2PT Made",
      "emoji": "\ud83c\udfc0"
    },
    {
      "period": 3,
      "clock": null,
      "teamId": 1268171,
      "teamName": "Duga",
      "player": "Fredrik Skogsj\u00f6",
      "playerNumber": "",
      "score": "35-54",
      "rawType": 109,
      "side": "Opponent",
      "kind": "foul",
      "label": "Personal Foul",
      "emoji": "\ud83e\udd4a"
    },
    {
      "period": 3,
      "clock": null,
      "teamId": 1264914,
      "teamName": "Kungsholmen OG",
      "player": "Niklas Walles",
      "playerNumber": "3",
      "score": "37-54",
      "rawType": 104,
      "side": "KOG",
      "kind": "score",
      "label": "2PT Made",
      "emoji": "\ud83c\udfc0"
    },
    {
      "period": 3,
      "clock": "10:00",
      "teamId": null,
      "teamName": "Duga",
      "player": "",
      "playerNumber": "",
      "score": "37-54",
      "rawType": 98,
      "side": null,
      "kind": "period",
      "label": "End Period 3",
      "emoji": "\ud83d\udd14",
      "detail": "Duga wins QTR 27-9, lead -17"
    },
    {
      "period": 4,
      "clock": "00:00",
      "teamId": null,
      "teamName": "Duga",
      "player": "",
      "playerNumber": "",
      "score": "37-54",
      "rawType": 99,
      "side": null,
      "kind": "period",
      "label": "Start Period 4",
      "emoji": "\u23f1\ufe0f"
    },
    {
      "period": 4,
      "clock": null,
      "teamId": 1264914,
      "teamName": "Kungsholmen OG",
      "player": "Axel Forsberg",
      "playerNumber": "13",
      "score": "39-54",
      "rawType": 104,
      "side": "KOG",
      "kind": "score",
      "label": "2PT Made",
      "emoji": "\ud83c\udfc0"
    },
    {
      "period": 4,
      "clock": null,
      "teamId": 1268171,
      "teamName": "Duga",
      "player": "Fredrik Skogsj\u00f6",
      "playerNumber": "",
      "score": "39-57",
      "rawType": 103,
      "side": "Opponent",
      "kind": "score",
      "label": "3PT Made",
      "emoji": "\ud83c\udfaf"
    },
    {
      "period": 4,
      "clock": null,
      "teamId": 1264914,
      "teamName": "Kungsholmen OG",
      "player": "Fares Cherif",
      "playerNumber": "5",
      "score": "41-57",
      "rawType": 104,
      "side": "KOG",
      "kind": "score",
      "label": "2PT Made",
      "emoji": "\ud83c\udfc0"
    },
    {
      "period": 4,
      "clock": null,
      "teamId": 1268171,
      "teamName": "Duga",
      "player": "Fredrik Skogsj\u00f6",
      "playerNumber": "",
      "score": "41-59",
      "rawType": 104,
      "side": "Opponent",
      "kind": "score",
      "label": "2PT Made",
      "emoji": "\ud83c\udfc0"
    },
    {
      "period": 4,
      "clock": null,
      "teamId": 1268171,
      "teamName": "Duga",
      "player": "Arvid Iverstam",
      "playerNumber": "88",
      "score": "41-61",
      "rawType": 104,
      "side": "Opponent",
      "kind": "score",
      "label": "2PT Made",
      "emoji": "\ud83c\udfc0"
    },
    {
      "period": 4,
      "clock": null,
      "teamId": 1268171,
      "teamName": "Duga",
      "player": "",
      "playerNumber": "",
      "score": "41-61",
      "rawType": 108,
      "side": "Opponent",
      "kind": "timeout",
      "label": "Timeout",
      "emoji": "\ud83d\uded1"
    },
    {
      "period": 4,
      "clock": null,
      "teamId": 1268171,
      "teamName": "Duga",
      "player": "Anton Andersson Andrejic",
      "playerNumber": "55",
      "score": "41-61",
      "rawType": 109,
      "side": "Opponent",
      "kind": "foul",
      "label": "Personal Foul",
      "emoji": "\ud83e\udd4a"
    },
    {
      "period": 4,
      "clock": null,
      "teamId": 1264914,
      "teamName": "Kungsholmen OG",
      "player": "Niklas Walles",
      "playerNumber": "3",
      "score": "42-61",
      "rawType": 106,
      "side": "KOG",
      "kind": "score",
      "label": "FT Made",
      "emoji": "\ud83c\udfab"
    },
    {
      "period": 4,
      "clock": null,
      "teamId": 1264914,
      "teamName": "Kungsholmen OG",
      "player": "Niklas Walles",
      "playerNumber": "3",
      "score": "43-61",
      "rawType": 106,
      "side": "KOG",
      "kind": "score",
      "label": "FT Made",
      "emoji": "\ud83c\udfab"
    },
    {
      "period": 4,
      "clock": null,
      "teamId": 1268171,
      "teamName": "Duga",
      "player": "Lucas Rudqwist",
      "playerNumber": "9",
      "score": "43-63",
      "rawType": 104,
      "side": "Opponent",
      "kind": "score",
      "label": "2PT Made",
      "emoji": "\ud83c\udfc0"
    },
    {
      "period": 4,
      "clock": null,
      "teamId": 1264914,
      "teamName": "Kungsholmen OG",
      "player": "Anton Jensen Wennberg",
      "playerNumber": "27",
      "score": "45-63",
      "rawType": 104,
      "side": "KOG",
      "kind": "score",
      "label": "2PT Made",
      "emoji": "\ud83c\udfc0"
    },
    {
      "period": 4,
      "clock": null,
      "teamId": 1268171,
      "teamName": "Duga",
      "player": "Anton Andersson Andrejic",
      "playerNumber": "55",
      "score": "45-66",
      "rawType": 103,
      "side": "Opponent",
      "kind": "score",
      "label": "3PT Made",
      "emoji": "\ud83c\udfaf"
    },
    {
      "period": 4,
      "clock": null,
      "teamId": 1268171,
      "teamName": "Duga",
      "player": "Daniel Mourad",
      "playerNumber": "12",
      "score": "45-68",
      "rawType": 104,
      "side": "Opponent",
      "kind": "score",
      "label": "2PT Made",
      "emoji": "\ud83c\udfc0"
    },
    {
      "period": 4,
      "clock": null,
      "teamId": 1264914,
      "teamName": "Kungsholmen OG",
      "player": "Niklas Walles",
      "playerNumber": "3",
      "score": "47-68",
      "rawType": 104,
      "side": "KOG",
      "kind": "score",
      "label": "2PT Made",
      "emoji": "\ud83c\udfc0"
    },
    {
      "period": 4,
      "clock": null,
      "teamId": 1268171,
      "teamName": "Duga",
      "player": "Lucas Rudqwist",
      "playerNumber": "9",
      "score": "47-70",
      "rawType": 104,
      "side": "Opponent",
      "kind": "score",
      "label": "2PT Made",
      "emoji": "\ud83c\udfc0"
    },
    {
      "period": 4,
      "clock": null,
      "teamId": 1264914,
      "teamName": "Kungsholmen OG",
      "player": "Joakim Walles",
      "playerNumber": "15",
      "score": "49-70",
      "rawType": 104,
      "side": "KOG",
      "kind": "score",
      "label": "2PT Made",
      "emoji": "\ud83c\udfc0"
    },
    {
      "period": 4,
      "clock": null,
      "teamId": 1268171,
      "teamName": "Duga",
      "player": "Simon \u00c5kerlund",
      "playerNumber": "5",
      "score": "49-72",
      "rawType": 104,
      "side": "Opponent",
      "kind": "score",
      "label": "2PT Made",
      "emoji": "\ud83c\udfc0"
    },
    {
      "period": 4,
      "clock": null,
      "teamId": 1268171,
      "teamName": "Duga",
      "player": "Fredrik Skogsj\u00f6",
      "playerNumber": "",
      "score": "49-74",
      "rawType": 104,
      "side": "Opponent",
      "kind": "score",
      "label": "2PT Made",
      "emoji": "\ud83c\udfc0"
    },
    {
      "period": 4,
      "clock": null,
      "teamId": 1268171,
      "teamName": "Duga",
      "player": "Simon \u00c5kerlund",
      "playerNumber": "5",
      "score": "49-76",
      "rawType": 104,
      "side": "Opponent",
      "kind": "score",
      "label": "2PT Made",
      "emoji": "\ud83c\udfc0"
    },
    {
      "period": 4,
      "clock": null,
      "teamId": 1264914,
      "teamName": "Kungsholmen OG",
      "player": "Anton Jensen Wennberg",
      "playerNumber": "27",
      "score": "51-76",
      "rawType": 104,
      "side": "KOG",
      "kind": "score",
      "label": "2PT Made",
      "emoji": "\ud83c\udfc0"
    },
    {
      "period": 4,
      "clock": null,
      "teamId": 1268171,
      "teamName": "Duga",
      "player": "Lucas Rudqwist",
      "playerNumber": "9",
      "score": "51-78",
      "rawType": 104,
      "side": "Opponent",
      "kind": "score",
      "label": "2PT Made",
      "emoji": "\ud83c\udfc0"
    },
    {
      "period": 4,
      "clock": null,
      "teamId": 1268171,
      "teamName": "Duga",
      "player": "Anton Andersson Andrejic",
      "playerNumber": "55",
      "score": "51-78",
      "rawType": 109,
      "side": "Opponent",
      "kind": "foul",
      "label": "Personal Foul",
      "emoji": "\ud83e\udd4a"
    },
    {
      "period": 4,
      "clock": null,
      "teamId": 1264914,
      "teamName": "Kungsholmen OG",
      "player": "Niklas Walles",
      "playerNumber": "3",
      "score": "52-78",
      "rawType": 106,
      "side": "KOG",
      "kind": "score",
      "label": "FT Made",
      "emoji": "\ud83c\udfab"
    },
    {
      "period": 4,
      "clock": null,
      "teamId": 1264914,
      "teamName": "Kungsholmen OG",
      "player": "Axel Forsberg",
      "playerNumber": "13",
      "score": "54-78",
      "rawType": 104,
      "side": "KOG",
      "kind": "score",
      "label": "2PT Made",
      "emoji": "\ud83c\udfc0"
    },
    {
      "period": 4,
      "clock": "10:00",
      "teamId": null,
      "teamName": "Duga",
      "player": "",
      "playerNumber": "",
      "score": "54-78",
      "rawType": 100,
      "side": null,
      "kind": "period",
      "label": "End Period 4",
      "emoji": "\ud83d\udd14",
      "detail": "Duga wins QTR 24-17, lead -24"
    },
    {
      "period": 4,
      "clock": "10:00",
      "teamId": null,
      "teamName": "Duga",
      "player": "",
      "playerNumber": "",
      "score": "54-78",
      "rawType": 100,
      "side": "Opponent",
      "kind": "period",
      "label": "Final Buzzer \u2014 Duga",
      "emoji": "\ud83c\udfc1"
    }
  ]
}